Workbook

Sheet README
A1: GRC Portfolio Project: Information Security Risk Register
A2: Fictional organisation: Northwind Financial Group | Version 1.0 | Prepared 2026-10-14
A4: COMPANY PROFILE
A5: Company | B5: Meridian Provisions Group (fictional): a global packaged-food manufacturer. About 6,200 employees, 14 plants across 9 countries, annual revenue about $2.4B, roughly 2,500 hybrid or remote office staff.
A6: Context | B6: The business is adopting AI (demand forecasting, plant analytics, customer service), moving to hybrid work, and facing climate-driven crop volatility and unstable global supply chains. These four forces drive most of the risks in this register.
A7: PURPOSE
A8: Purpose | B8: An enterprise risk register showing the full risk lifecycle: identify, assess (inherent), apply controls, reassess (residual), treat, assign ownership, monitor with KRIs, and report to leadership.
A9: Methodology | B9: Aligned to ISO 31000. Controls and actions reference ISO 22301 (continuity), ISO 28000 (supply chain security), ISO 27001 (information security), NIST AI RMF and ISO/IEC 42001 (AI), IEC 62443 (OT), and TCFD / ISSB IFRS S2 (climate).
A10: Scoring | B10: 5x5 qualitative matrix. Risk Score = Likelihood x Impact (1-25). Bands: Low 1-4, Medium 5-9, High 10-14, Critical 15-25. Thresholds live on the 'Scoring' sheet and drive every rating.
A11: SHEETS
A12: Risk Register | B12: 75 sample risks in 13 categories (6 cyber security sub-categories), 27 columns, auto-calculated scores, ratings, appetite check and next review date. Formulas are pre-filled to row 105 so you can add risks.
A13: Dashboard | B13: Executive view: KPIs, inherent vs residual chart, category chart, status and treatment breakdowns, and the Top 5 residual risks.
A14: Heat Map | B14: 5x5 heat maps (inherent and residual) showing how many risks sit in each Likelihood x Impact cell.
A15: Scoring | B15: Likelihood scale, impact scale, rating bands, required response, review frequency, and the risk appetite threshold.
A16: Lists | B16: Dropdown values used for data validation (categories, control effectiveness, treatment, status).
A17: HOW TO USE
A18: Add a risk | B18: Type in the next empty row of 'Risk Register'. Fill blue-text input columns only; black columns calculate automatically.
A19: Change appetite | B19: Edit the yellow cell on the 'Scoring' sheet. 'Within Appetite?' and the dashboard update automatically.
A20: Colour key | B20: Blue text = input. Black text = formula. Yellow fill = key assumption you can change.
A21: ASSUMPTIONS
A22: Fictional data | B22: Meridian Provisions Group, its sites, suppliers, figures, owners (shown as roles, not names), dates and KRIs are invented for portfolio purposes. No real company data is used.
A23: Financial scale | B23: Impact dollar thresholds on 'Scoring' are scaled to a $2.4B revenue company and are illustrative. Calibrate them to a real organisation.
A24: Appetite | B24: Residual score of 9 or below (Medium or lower) is treated as within appetite. This is an assumption, editable on 'Scoring'.
A25: Review cycle | B25: Next review = Last Review + frequency for the residual rating (Critical 30, High 90, Medium 180, Low 365 days). Assumption, editable on 'Scoring'.
A26: Heat map colours | B26: Heat map cell colours are fixed to the default bands. If you change band thresholds, recolour the heat map cells manually.
A27: Helper column | B27: Column AB on 'Risk Register' is a hidden helper used to rank the Top 5 on the dashboard. Do not delete it.

Sheet Risk Register
A1: Enterprise Risk Register
A2: Meridian Provisions Group (fictional) | ISO 31000 aligned | 5x5 scoring | Themes: cyber security, AI adoption, hybrid work, climate change, supply chain
A3: Key: blue text = input, black = auto-calculated. Scores, ratings, appetite check and next review date update automatically. Rows 6-80 are illustrative sample data; formulas are pre-filled to row 105.
A5: Risk ID | B5: Date Identified | C5: Category | D5: Risk Title | E5: Risk Description (Cause > Event > Impact) | F5: Affected Asset / Process | G5: Risk Owner | H5: Inherent Likelihood (1-5) | I5: Inherent Impact (1-5) | J5: Inherent Score | K5: Inherent Rating | L5: Existing Controls | M5: Framework Mapping (ISO / NIST / TCFD / ISSB) | N5: Control Effectiveness | O5: Residual Likelihood (1-5) | P5: Residual Impact (1-5) | Q5: Residual Score | R5: Residual Rating | S5: Within Appetite? | T5: Treatment | U5: Treatment Plan / Action | V5: Action Owner | W5: Target Date | X5: Status | Y5: Key Risk Indicator (KRI) | Z5: Last Review | AA5: Next Review | AB5: Sort Key (helper)
A6: R-001 | B6: 46035 | C6: Climate & Environment | D6: Heat and drought cut yields of key crop inputs | E6: Due to more frequent heatwaves and drought in sourcing regions (wheat, cocoa, sunflower oil), supply volumes could fall and input prices spike, compressing margins and causing stockouts of flagship products. | F6: Raw ingredient sourcing (top 5 crops) | G6: Chief Procurement Officer | H6: 4 | I6: 4 | J6: =IF(OR(H6="",I6=""),"",H6*I6) -> 16 | K6: =IF(J6="","",IF(J6>=Scoring!$B$24,"Critical",IF(J6>=Scoring!$B$23,"High",IF(J6>=Scoring!$B$22,"Medium","Low")))) -> Critical | L6: Multi-origin sourcing for top 5 ingredients; forward contracts covering about 60% of annual volume; supplier crop-monitoring programme. | M6: ISO 31000 6.4 | TCFD Strategy | ISSB IFRS S2 (physical risk) | N6: Adequate | O6: 3 | P6: 3 | Q6: =IF(OR(O6="",P6=""),"",O6*P6) -> 9 | R6: =IF(Q6="","",IF(Q6>=Scoring!$B$24,"Critical",IF(Q6>=Scoring!$B$23,"High",IF(Q6>=Scoring!$B$22,"Medium","Low")))) -> Medium | S6: =IF(Q6="","",IF(Q6<=Scoring!$B$27,"Yes","No")) -> Yes | T6: Mitigate | U6: Qualify alternate origins for cocoa and wheat; prepare reformulation options for 3 SKUs; run 2C and 4C climate scenario analysis. | V6: Head of Strategic Sourcing | W6: 46477 | X6: In Progress | Y6: % volume from single origin (target <30%); forward cover % | Z6: 46301 | AA6: =IF(OR(Z6="",R6=""),"",Z6+INDEX(Scoring!$E$21:$E$24,MATCH(R6,Scoring!$A$21:$A$24,0))) -> 46481 | AB6: =IF(Q6="","",Q6+(1000-ROW())/100000) -> 9.00994
A7: R-002 | B7: 46035 | C7: Climate & Environment | D7: Flooding and storm damage at coastal plants | E7: Four of 14 plants sit in flood-prone coastal zones. A major storm or flood could halt production for weeks and damage equipment and inventory. | F7: Plants 3, 5, 9 and 11 | G7: Chief Operating Officer | H7: 3 | I7: 5 | J7: =IF(OR(H7="",I7=""),"",H7*I7) -> 15 | K7: =IF(J7="","",IF(J7>=Scoring!$B$24,"Critical",IF(J7>=Scoring!$B$23,"High",IF(J7>=Scoring!$B$22,"Medium","Low")))) -> Critical | L7: Site flood-risk assessments; business interruption insurance; flood barriers at 2 sites; emergency response plans. | M7: ISO 14090 (adaptation) | ISO 22301 | TCFD Risk Management | N7: Adequate | O7: 3 | P7: 4 | Q7: =IF(OR(O7="",P7=""),"",O7*P7) -> 12 | R7: =IF(Q7="","",IF(Q7>=Scoring!$B$24,"Critical",IF(Q7>=Scoring!$B$23,"High",IF(Q7>=Scoring!$B$22,"Medium","Low")))) -> High | S7: =IF(Q7="","",IF(Q7<=Scoring!$B$27,"Yes","No")) -> No | T7: Transfer | U7: Install barriers and raise critical equipment at remaining 2 sites; review insurance sublimits and parametric cover options. | V7: Head of EHS & Facilities | W7: 46568 | X7: Open | Y7: Sites with completed adaptation plan (target 4 of 4); insurance sublimit vs modelled loss | Z7: 46289 | AA7: =IF(OR(Z7="",R7=""),"",Z7+INDEX(Scoring!$E$21:$E$24,MATCH(R7,Scoring!$A$21:$A$24,0))) -> 46379 | AB7: =IF(Q7="","",Q7+(1000-ROW())/100000) -> 12.00993
A8: R-003 | B8: 46055 | C8: Supply Chain & Logistics | D8: Maritime chokepoint disruption extends lead times | E8: Due to geopolitical tension and extreme weather near major shipping lanes (e.g. Red Sea, Panama Canal), inbound ingredient and packaging deliveries could be delayed, raising freight costs and causing line stoppages. | F8: Ocean freight, inbound logistics | G8: Chief Supply Chain Officer | H8: 4 | I8: 4 | J8: =IF(OR(H8="",I8=""),"",H8*I8) -> 16 | K8: =IF(J8="","",IF(J8>=Scoring!$B$24,"Critical",IF(J8>=Scoring!$B$23,"High",IF(J8>=Scoring!$B$22,"Medium","Low")))) -> Critical | L8: Freight contracts with rerouting clauses; 3 weeks safety stock on 25 critical SKUs; logistics control tower. | M8: ISO 28000 | ISO 22301 | ISO 31000 | N8: Adequate | O8: 3 | P8: 3 | Q8: =IF(OR(O8="",P8=""),"",O8*P8) -> 9 | R8: =IF(Q8="","",IF(Q8>=Scoring!$B$24,"Critical",IF(Q8>=Scoring!$B$23,"High",IF(Q8>=Scoring!$B$22,"Medium","Low")))) -> Medium | S8: =IF(Q8="","",IF(Q8<=Scoring!$B$27,"Yes","No")) -> Yes | T8: Mitigate | U8: Nearshore two packaging lines; adopt dual-port strategy for EU imports. | V8: Head of Logistics | W8: 46446 | X8: In Progress | Y8: Inbound lead time vs baseline; days of inventory on critical SKUs | Z8: 46303 | AA8: =IF(OR(Z8="",R8=""),"",Z8+INDEX(Scoring!$E$21:$E$24,MATCH(R8,Scoring!$A$21:$A$24,0))) -> 46483 | AB8: =IF(Q8="","",Q8+(1000-ROW())/100000) -> 9.00992
A9: R-004 | B9: 46055 | C9: Supply Chain & Logistics | D9: Single-source dependency for specialty packaging film | E9: Due to reliance on one supplier, a plant fire, insolvency or export restriction could stop packaging for 40% of the product range. | F9: Packaging film (Tier-1 supplier) | G9: Chief Procurement Officer | H9: 3 | I9: 5 | J9: =IF(OR(H9="",I9=""),"",H9*I9) -> 15 | K9: =IF(J9="","",IF(J9>=Scoring!$B$24,"Critical",IF(J9>=Scoring!$B$23,"High",IF(J9>=Scoring!$B$22,"Medium","Low")))) -> Critical | L9: 3-year supply contract; 6 weeks buffer stock; supplier financial health monitoring. | M9: ISO 28000 | ISO 22301 | ISO 31000 | N9: Weak | O9: 3 | P9: 4 | Q9: =IF(OR(O9="",P9=""),"",O9*P9) -> 12 | R9: =IF(Q9="","",IF(Q9>=Scoring!$B$24,"Critical",IF(Q9>=Scoring!$B$23,"High",IF(Q9>=Scoring!$B$22,"Medium","Low")))) -> High | S9: =IF(Q9="","",IF(Q9<=Scoring!$B$27,"Yes","No")) -> No | T9: Mitigate | U9: Qualify second supplier; trial recyclable mono-material alternative film. | V9: Packaging Category Manager | W9: 46295 | X9: In Progress | Y9: % spend with sole-source suppliers; supplier on-time-in-full rate | Z9: 46293 | AA9: =IF(OR(Z9="",R9=""),"",Z9+INDEX(Scoring!$E$21:$E$24,MATCH(R9,Scoring!$A$21:$A$24,0))) -> 46383 | AB9: =IF(Q9="","",Q9+(1000-ROW())/100000) -> 12.00991
A10: R-005 | B10: 46069 | C10: Supply Chain & Logistics | D10: Tariffs and trade restrictions disrupt cross-border flows | E10: Due to shifting trade policy, new tariffs or import bans could raise landed costs and force rapid changes to sourcing and pricing. | F10: Cross-border trade flows (9 countries) | G10: Head of Trade Compliance | H10: 4 | I10: 3 | J10: =IF(OR(H10="",I10=""),"",H10*I10) -> 12 | K10: =IF(J10="","",IF(J10>=Scoring!$B$24,"Critical",IF(J10>=Scoring!$B$23,"High",IF(J10>=Scoring!$B$22,"Medium","Low")))) -> High | L10: Trade compliance team; tariff scenario modelling; duty drawback programmes. | M10: ISO 31000 | ISO 28000 | N10: Adequate | O10: 3 | P10: 3 | Q10: =IF(OR(O10="",P10=""),"",O10*P10) -> 9 | R10: =IF(Q10="","",IF(Q10>=Scoring!$B$24,"Critical",IF(Q10>=Scoring!$B$23,"High",IF(Q10>=Scoring!$B$22,"Medium","Low")))) -> Medium | S10: =IF(Q10="","",IF(Q10<=Scoring!$B$27,"Yes","No")) -> Yes | T10: Mitigate | U10: Re-map bill of materials by country of origin; add tariff pass-through clauses to key customer contracts. | V10: Trade Compliance Manager | W10: 46418 | X10: Open | Y10: Tariff cost as % of COGS; SKUs with single country-of-origin exposure | Z10: 46283 | AA10: =IF(OR(Z10="",R10=""),"",Z10+INDEX(Scoring!$E$21:$E$24,MATCH(R10,Scoring!$A$21:$A$24,0))) -> 46463 | AB10: =IF(Q10="","",Q10+(1000-ROW())/100000) -> 9.0099
A11: R-006 | B11: 46083 | C11: Regulatory & ESG | D11: Tier-2 supplier forced labour or deforestation non-compliance | E11: Due to limited visibility beyond Tier-1, suppliers could use forced labour or deforested land, triggering import bans, fines and brand damage under due diligence laws (e.g. EU CSDDD, EUDR). | F11: Palm oil and cocoa supply chains | G11: Chief Sustainability Officer | H11: 3 | I11: 4 | J11: =IF(OR(H11="",I11=""),"",H11*I11) -> 12 | K11: =IF(J11="","",IF(J11>=Scoring!$B$24,"Critical",IF(J11>=Scoring!$B$23,"High",IF(J11>=Scoring!$B$22,"Medium","Low")))) -> High | L11: Supplier code of conduct; annual Tier-1 audits; third-party ESG ratings. | M11: ISO 20400 | ISO 31000 | ISSB IFRS S1 | N11: Adequate | O11: 2 | P11: 4 | Q11: =IF(OR(O11="",P11=""),"",O11*P11) -> 8 | R11: =IF(Q11="","",IF(Q11>=Scoring!$B$24,"Critical",IF(Q11>=Scoring!$B$23,"High",IF(Q11>=Scoring!$B$22,"Medium","Low")))) -> Medium | S11: =IF(Q11="","",IF(Q11<=Scoring!$B$27,"Yes","No")) -> Yes | T11: Mitigate | U11: Map Tier-2 for palm oil and cocoa; deploy traceability platform; add audit rights to contracts. | V11: Head of Sustainability | W11: 46507 | X11: In Progress | Y11: % volume traced to farm or mill; supplier audit non-conformities closed on time | Z11: 46286 | AA11: =IF(OR(Z11="",R11=""),"",Z11+INDEX(Scoring!$E$21:$E$24,MATCH(R11,Scoring!$A$21:$A$24,0))) -> 46466 | AB11: =IF(Q11="","",Q11+(1000-ROW())/100000) -> 8.00989
A12: R-007 | B12: 46097 | C12: Regulatory & ESG | D12: Carbon pricing and climate disclosure mandates raise costs | E12: Due to expanding carbon pricing and mandatory climate reporting, compliance and energy costs could rise and missed targets could attract investor and regulator scrutiny. | F12: Scope 1-3 emissions, capex plan | G12: Chief Financial Officer | H12: 4 | I12: 3 | J12: =IF(OR(H12="",I12=""),"",H12*I12) -> 12 | K12: =IF(J12="","",IF(J12>=Scoring!$B$24,"Critical",IF(J12>=Scoring!$B$23,"High",IF(J12>=Scoring!$B$22,"Medium","Low")))) -> High | L12: Scope 1-2 baseline; internal carbon price in capex decisions; net-zero roadmap. | M12: ISSB IFRS S2 | GHG Protocol | TCFD Metrics & Targets | N12: Adequate | O12: 3 | P12: 3 | Q12: =IF(OR(O12="",P12=""),"",O12*P12) -> 9 | R12: =IF(Q12="","",IF(Q12>=Scoring!$B$24,"Critical",IF(Q12>=Scoring!$B$23,"High",IF(Q12>=Scoring!$B$22,"Medium","Low")))) -> Medium | S12: =IF(Q12="","",IF(Q12<=Scoring!$B$27,"Yes","No")) -> Yes | T12: Mitigate | U12: Complete Scope 3 baseline; sign renewable PPAs and efficiency upgrades at 5 most energy-intensive plants. | V12: Head of Sustainability | W12: 46507 | X12: In Progress | Y12: Scope 1+2 tCO2e vs target; carbon cost exposure ($M) | Z12: 46296 | AA12: =IF(OR(Z12="",R12=""),"",Z12+INDEX(Scoring!$E$21:$E$24,MATCH(R12,Scoring!$A$21:$A$24,0))) -> 46476 | AB12: =IF(Q12="","",Q12+(1000-ROW())/100000) -> 9.00988
A13: R-008 | B13: 46118 | C13: Technology & AI | D13: Confidential data leakage through generative AI tools | E13: Due to unmanaged use of public AI tools, staff may paste recipes, supplier pricing or customer data into external services, causing loss of IP and possible contractual or privacy breaches. | F13: Employees, IP, supplier contracts | G13: Chief Information Security Officer | H13: 4 | I13: 4 | J13: =IF(OR(H13="",I13=""),"",H13*I13) -> 16 | K13: =IF(J13="","",IF(J13>=Scoring!$B$24,"Critical",IF(J13>=Scoring!$B$23,"High",IF(J13>=Scoring!$B$22,"Medium","Low")))) -> Critical | L13: AI acceptable use policy; approved enterprise AI tool with no-training terms; partial web filtering and DLP. | M13: NIST AI RMF (Govern, Manage) | ISO/IEC 42001 | ISO 27001 A.8.12 | N13: Adequate | O13: 3 | P13: 3 | Q13: =IF(OR(O13="",P13=""),"",O13*P13) -> 9 | R13: =IF(Q13="","",IF(Q13>=Scoring!$B$24,"Critical",IF(Q13>=Scoring!$B$23,"High",IF(Q13>=Scoring!$B$22,"Medium","Low")))) -> Medium | S13: =IF(Q13="","",IF(Q13<=Scoring!$B$27,"Yes","No")) -> Yes | T13: Mitigate | U13: Deploy DLP rules for external AI services; publish AI tool register; mandatory AI-use training. | V13: Head of Data Governance | W13: 46402 | X13: In Progress | Y13: DLP events to unapproved AI services; % staff trained on AI policy | Z13: 46304 | AA13: =IF(OR(Z13="",R13=""),"",Z13+INDEX(Scoring!$E$21:$E$24,MATCH(R13,Scoring!$A$21:$A$24,0))) -> 46484 | AB13: =IF(Q13="","",Q13+(1000-ROW())/100000) -> 9.00987
A14: R-009 | B14: 46118 | C14: Technology & AI | D14: AI demand forecast drift causes inventory errors | E14: Due to volatile post-disruption demand, the AI forecasting model may drift from reality, causing overstock, waste of perishable stock or stockouts. | F14: Demand planning, S&OP process | G14: Chief Data & AI Officer | H14: 4 | I14: 3 | J14: =IF(OR(H14="",I14=""),"",H14*I14) -> 12 | K14: =IF(J14="","",IF(J14>=Scoring!$B$24,"Critical",IF(J14>=Scoring!$B$23,"High",IF(J14>=Scoring!$B$22,"Medium","Low")))) -> High | L14: Model performance dashboard; planner override capability; quarterly retraining. | M14: NIST AI RMF (Measure, Manage) | ISO/IEC 42001 | N14: Adequate | O14: 3 | P14: 2 | Q14: =IF(OR(O14="",P14=""),"",O14*P14) -> 6 | R14: =IF(Q14="","",IF(Q14>=Scoring!$B$24,"Critical",IF(Q14>=Scoring!$B$23,"High",IF(Q14>=Scoring!$B$22,"Medium","Low")))) -> Medium | S14: =IF(Q14="","",IF(Q14<=Scoring!$B$27,"Yes","No")) -> Yes | T14: Mitigate | U14: Add drift detection and human approval for forecasts with more than 15% variance; run champion-challenger testing. | V14: ML Engineering Lead | W14: 46305 | X14: In Progress | Y14: Forecast error WAPE (target <20%); open drift alerts | Z14: 46298 | AA14: =IF(OR(Z14="",R14=""),"",Z14+INDEX(Scoring!$E$21:$E$24,MATCH(R14,Scoring!$A$21:$A$24,0))) -> 46478 | AB14: =IF(Q14="","",Q14+(1000-ROW())/100000) -> 6.00986
A15: R-010 | B15: 46132 | C15: Technology & AI | D15: Biased or non-compliant AI in hiring and customer service | E15: Due to weak AI governance, automated CV screening or chatbots could produce discriminatory outcomes or breach AI regulation (e.g. EU AI Act high-risk employment use), leading to fines, claims and reputational damage. | F15: HR recruitment, customer service | G15: General Counsel | H15: 3 | I15: 4 | J15: =IF(OR(H15="",I15=""),"",H15*I15) -> 12 | K15: =IF(J15="","",IF(J15>=Scoring!$B$24,"Critical",IF(J15>=Scoring!$B$23,"High",IF(J15>=Scoring!$B$22,"Medium","Low")))) -> High | L15: AI use-case intake form; legal review of vendors (partial). | M15: EU AI Act | NIST AI RMF (Map) | ISO/IEC 42001 | N15: Weak | O15: 3 | P15: 3 | Q15: =IF(OR(O15="",P15=""),"",O15*P15) -> 9 | R15: =IF(Q15="","",IF(Q15>=Scoring!$B$24,"Critical",IF(Q15>=Scoring!$B$23,"High",IF(Q15>=Scoring!$B$22,"Medium","Low")))) -> Medium | S15: =IF(Q15="","",IF(Q15<=Scoring!$B$27,"Yes","No")) -> Yes | T15: Avoid | U15: Pause automated CV screening pilot; limit AI to scheduling; re-evaluate after bias testing and vendor conformity evidence. | V15: AI Governance Lead | W15: 46446 | X15: Open | Y15: % AI use cases risk-classified; bias test pass rate | Z15: 46295 | AA15: =IF(OR(Z15="",R15=""),"",Z15+INDEX(Scoring!$E$21:$E$24,MATCH(R15,Scoring!$A$21:$A$24,0))) -> 46475 | AB15: =IF(Q15="","",Q15+(1000-ROW())/100000) -> 9.00985
A16: R-011 | B16: 46146 | C16: Cyber: Identity & Access | D16: Deepfake-enabled payment fraud and executive impersonation | E16: Due to realistic AI voice and video cloning, staff could be tricked into releasing payments or changing supplier bank details, causing direct financial loss. | F16: Treasury, accounts payable | G16: Chief Financial Officer | H16: 3 | I16: 4 | J16: =IF(OR(H16="",I16=""),"",H16*I16) -> 12 | K16: =IF(J16="","",IF(J16>=Scoring!$B$24,"Critical",IF(J16>=Scoring!$B$23,"High",IF(J16>=Scoring!$B$22,"Medium","Low")))) -> High | L16: Dual approval for payments above $50k; call-back verification for bank detail changes; fraud awareness. | M16: ISO 27001 A.5.3, A.6.3 | NIST CSF 2.0 PR.AT | N16: Adequate | O16: 2 | P16: 3 | Q16: =IF(OR(O16="",P16=""),"",O16*P16) -> 6 | R16: =IF(Q16="","",IF(Q16>=Scoring!$B$24,"Critical",IF(Q16>=Scoring!$B$23,"High",IF(Q16>=Scoring!$B$22,"Medium","Low")))) -> Medium | S16: =IF(Q16="","",IF(Q16<=Scoring!$B$27,"Yes","No")) -> Yes | T16: Mitigate | U16: Introduce out-of-band codeword verification for executive payment requests; run deepfake awareness drills. | V16: Treasury Controller | W16: 46387 | X16: Open | Y16: Fraud attempts detected vs lost; % payment staff trained | Z16: 46281 | AA16: =IF(OR(Z16="",R16=""),"",Z16+INDEX(Scoring!$E$21:$E$24,MATCH(R16,Scoring!$A$21:$A$24,0))) -> 46461 | AB16: =IF(Q16="","",Q16+(1000-ROW())/100000) -> 6.00984
A17: R-012 | B17: 46160 | C17: Cyber: OT & Third-Party | D17: Ransomware targeting plant operational technology (OT) | E17: Connecting plant systems to AI analytics widens the attack surface. Ransomware could stop production lines, spoil perishable stock and delay deliveries. | F17: OT networks at 14 plants | G17: Chief Information Security Officer | H17: 4 | I17: 5 | J17: =IF(OR(H17="",I17=""),"",H17*I17) -> 20 | K17: =IF(J17="","",IF(J17>=Scoring!$B$24,"Critical",IF(J17>=Scoring!$B$23,"High",IF(J17>=Scoring!$B$22,"Medium","Low")))) -> Critical | L17: IT/OT segmentation at 9 of 14 plants; EDR on IT systems; offline backups; OT incident plan. | M17: IEC 62443 | NIST CSF 2.0 PR.IR | ISO 27001 A.8.22 | N17: Weak | O17: 3 | P17: 4 | Q17: =IF(OR(O17="",P17=""),"",O17*P17) -> 12 | R17: =IF(Q17="","",IF(Q17>=Scoring!$B$24,"Critical",IF(Q17>=Scoring!$B$23,"High",IF(Q17>=Scoring!$B$22,"Medium","Low")))) -> High | S17: =IF(Q17="","",IF(Q17<=Scoring!$B$27,"Yes","No")) -> No | T17: Mitigate | U17: Segment remaining 5 plants; build OT asset inventory with passive monitoring; run manual-mode production drills. | V17: Head of OT Security | W17: 46568 | X17: In Progress | Y17: % plants with IT/OT segmentation (target 100%); % OT assets visible | Z17: 46300 | AA17: =IF(OR(Z17="",R17=""),"",Z17+INDEX(Scoring!$E$21:$E$24,MATCH(R17,Scoring!$A$21:$A$24,0))) -> 46390 | AB17: =IF(Q17="","",Q17+(1000-ROW())/100000) -> 12.00983
... A26: R-021 | B26: 46266 | C26: Regulatory & ESG | D26: Greenwashing allegations from inaccurate sustainability claims | E26: Due to weak substantiation, product and corporate environmental claims could be challenged, leading to fines, product relabelling and loss of consumer trust. | F26: Packaging claims, marketing | G26: General Counsel | H26: 3 | I26: 4 | J26: =IF(OR(H26="",I26=""),"",H26*I26) -> 12 | K26: =IF(J26="","",IF(J26>=Scoring!$B$24,"Critical",IF(J26>=Scoring!$B$23,"High",IF(J26>=Scoring!$B$22,"Medium","Low")))) -> High | L26: Legal review of claims (ad hoc); sustainability reporting team. | M26: ISO 14021 | ISSB IFRS S1 | N26: Adequate | O26: 2 | P26: 3 | Q26: =IF(OR(O26="",P26=""),"",O26*P26) -> 6 | R26: =IF(Q26="","",IF(Q26>=Scoring!$B$24,"Critical",IF(Q26>=Scoring!$B$23,"High",IF(Q26>=Scoring!$B$22,"Medium","Low")))) -> Medium | S26: =IF(Q26="","",IF(Q26<=Scoring!$B$27,"Yes","No")) -> Yes | T26: Mitigate | U26: Keep evidence file for every environmental claim; obtain third-party assurance of climate data. | V26: Head of Brand Compliance | W26: 46446 | X26: Open | Y26: % claims with evidence file (target 100%); regulator or complaint cases | Z26: 46307 | AA26: =IF(OR(Z26="",R26=""),"",Z26+INDEX(Scoring!$E$21:$E$24,MATCH(R26,Scoring!$A$21:$A$24,0))) -> 46487 | AB26: =IF(Q26="","",Q26+(1000-ROW())/100000) -> 6.00974
A27: R-022 | B27: 46279 | C27: Operational Resilience | D27: Pandemic or health event disrupts workforce and plants | E27: Due to a new outbreak, absenteeism could reduce plant output and disrupt logistics, although remote capability and cross-training reduce exposure. | F27: Workforce, plants | G27: Chief Operating Officer | H27: 2 | I27: 4 | J27: =IF(OR(H27="",I27=""),"",H27*I27) -> 8 | K27: =IF(J27="","",IF(J27>=Scoring!$B$24,"Critical",IF(J27>=Scoring!$B$23,"High",IF(J27>=Scoring!$B$22,"Medium","Low")))) -> Medium | L27: Pandemic plan; cross-trained operators; proven remote work capability. | M27: ISO 22301 | ISO 45001 | N27: Strong | O27: 2 | P27: 3 | Q27: =IF(OR(O27="",P27=""),"",O27*P27) -> 6 | R27: =IF(Q27="","",IF(Q27>=Scoring!$B$24,"Critical",IF(Q27>=Scoring!$B$23,"High",IF(Q27>=Scoring!$B$22,"Medium","Low")))) -> Medium | S27: =IF(Q27="","",IF(Q27<=Scoring!$B$27,"Yes","No")) -> Yes | T27: Accept | U27: Accept residual risk; test pandemic plan annually. | V27: Head of EHS & Facilities | X27: Monitoring | Y27: Absence rate vs baseline; plan test completed | Z27: 46296 | AA27: =IF(OR(Z27="",R27=""),"",Z27+INDEX(Scoring!$E$21:$E$24,MATCH(R27,Scoring!$A$21:$A$24,0))) -> 46476 | AB27: =IF(Q27="","",Q27+(1000-ROW())/100000) -> 6.00973
A28: R-023 | B28: 46042 | C28: Cyber: Identity & Access | D28: Compromise of privileged and domain admin accounts | E28: Due to credential theft or weak admin hygiene, an attacker could gain domain-level control, enabling mass data theft, ransomware deployment and persistent access. | F28: Active Directory, Entra ID, admin accounts | G28: Chief Information Security Officer | H28: 3 | I28: 5 | J28: =IF(OR(H28="",I28=""),"",H28*I28) -> 15 | K28: =IF(J28="","",IF(J28>=Scoring!$B$24,"Critical",IF(J28>=Scoring!$B$23,"High",IF(J28>=Scoring!$B$22,"Medium","Low")))) -> Critical | L28: Separate admin accounts; PAM vault with session recording; tiered admin model (partial). | M28: ISO 27001 A.8.2, A.5.18 | NIST PR.AA | CIS 5, 6 | N28: Adequate | O28: 2 | P28: 4 | Q28: =IF(OR(O28="",P28=""),"",O28*P28) -> 8 | R28: =IF(Q28="","",IF(Q28>=Scoring!$B$24,"Critical",IF(Q28>=Scoring!$B$23,"High",IF(Q28>=Scoring!$B$22,"Medium","Low")))) -> Medium | S28: =IF(Q28="","",IF(Q28<=Scoring!$B$27,"Yes","No")) -> Yes | T28: Mitigate | U28: Complete tiered admin model; enforce just-in-time admin access; rotate break-glass credentials. | V28: Head of Identity & Access | W28: 46477 | X28: In Progress | Y28: % privileged accounts in PAM (target 100%); standing admin accounts | Z28: 46252 | AA28: =IF(OR(Z28="",R28=""),"",Z28+INDEX(Scoring!$E$21:$E$24,MATCH(R28,Scoring!$A$21:$A$24,0))) -> 46432 | AB28: =IF(Q28="","",Q28+(1000-ROW())/100000) -> 8.00972
A29: R-024 | B29: 46047 | C29: Cyber: Identity & Access | D29: MFA fatigue and push-bombing attacks | E29: Attackers flood users with MFA prompts until one is approved, bypassing authentication and gaining access to email and VPN. | F29: Corporate SSO, VPN | G29: Head of Identity & Access | H29: 4 | I29: 3 | J29: =IF(OR(H29="",I29=""),"",H29*I29) -> 12 | K29: =IF(J29="","",IF(J29>=Scoring!$B$24,"Critical",IF(J29>=Scoring!$B$23,"High",IF(J29>=Scoring!$B$22,"Medium","Low")))) -> High | L29: Push-based MFA; number matching on VPN only; lockout after repeated denials. | M29: ISO 27001 A.8.5 | NIST PR.AA | CIS 6 | N29: Adequate | O29: 3 | P29: 2 | Q29: =IF(OR(O29="",P29=""),"",O29*P29) -> 6 | R29: =IF(Q29="","",IF(Q29>=Scoring!$B$24,"Critical",IF(Q29>=Scoring!$B$23,"High",IF(Q29>=Scoring!$B$22,"Medium","Low")))) -> Medium | S29: =IF(Q29="","",IF(Q29<=Scoring!$B$27,"Yes","No")) -> Yes | T29: Mitigate | U29: Enable number matching and location context everywhere; move high-risk users to FIDO2 keys. | V29: Identity & Access Manager | W29: 46371 | X29: In Progress | Y29: MFA denial spikes per week; % users on phishing-resistant MFA | Z29: 46259 | AA29: =IF(OR(Z29="",R29=""),"",Z29+INDEX(Scoring!$E$21:$E$24,MATCH(R29,Scoring!$A$21:$A$24,0))) -> 46439 | AB29: =IF(Q29="","",Q29+(1000-ROW())/100000) -> 6.00971
A30: R-025 | B30: 46052 | C30: Cyber: Identity & Access | D30: Orphaned and dormant accounts after offboarding | E30: Leavers and role changes are not always reflected in all systems, leaving active accounts that could be misused. | F30: HR-linked systems, SaaS apps | G30: Chief Information Officer | H30: 4 | I30: 3 | J30: =IF(OR(H30="",I30=""),"",H30*I30) -> 12 | K30: =IF(J30="","",IF(J30>=Scoring!$B$24,"Critical",IF(J30>=Scoring!$B$23,"High",IF(J30>=Scoring!$B$22,"Medium","Low")))) -> High | L30: Manual leaver checklist; quarterly dormant account report. | M30: ISO 27001 A.5.16, A.5.18, A.6.5 | NIST PR.AA | N30: Weak | O30: 3 | P30: 2 | Q30: =IF(OR(O30="",P30=""),"",O30*P30) -> 6 | R30: =IF(Q30="","",IF(Q30>=Scoring!$B$24,"Critical",IF(Q30>=Scoring!$B$23,"High",IF(Q30>=Scoring!$B$22,"Medium","Low")))) -> Medium | S30: =IF(Q30="","",IF(Q30<=Scoring!$B$27,"Yes","No")) -> Yes | T30: Mitigate | U30: Integrate HR system with identity provider for automated deprovisioning within 24 hours. | V30: IAM Engineering Lead | W30: 46418 | X30: In Progress | Y30: Leaver accounts active >7 days (target 0); dormant accounts >90 days | Z30: 46266 | AA30: =IF(OR(Z30="",R30=""),"",Z30+INDEX(Scoring!$E$21:$E$24,MATCH(R30,Scoring!$A$21:$A$24,0))) -> 46446 | AB30: =IF(Q30="","",Q30+(1000-ROW())/100000) -> 6.0097
A31: R-026 | B31: 46057 | C31: Cyber: Identity & Access | D31: Privilege creep and segregation-of-duties conflicts in ERP | E31: Over time staff accumulate access beyond role needs, enabling fraud or accidental changes and failing segregation of duties. | F31: ERP, finance systems | G31: Chief Financial Officer | H31: 4 | I31: 3 | J31: =IF(OR(H31="",I31=""),"",H31*I31) -> 12 | K31: =IF(J31="","",IF(J31>=Scoring!$B$24,"Critical",IF(J31>=Scoring!$B$23,"High",IF(J31>=Scoring!$B$22,"Medium","Low")))) -> High | L31: Role-based access; annual access recertification; limited SoD rule set. | M31: ISO 27001 A.5.3, A.5.15, A.5.18 | NIST PR.AA | ITGC | N31: Adequate | O31: 3 | P31: 2 | Q31: =IF(OR(O31="",P31=""),"",O31*P31) -> 6 | R31: =IF(Q31="","",IF(Q31>=Scoring!$B$24,"Critical",IF(Q31>=Scoring!$B$23,"High",IF(Q31>=Scoring!$B$22,"Medium","Low")))) -> Medium | S31: =IF(Q31="","",IF(Q31<=Scoring!$B$27,"Yes","No")) -> Yes | T31: Mitigate | U31: Run SoD conflict analysis; move finance roles to quarterly recertification. | V31: ERP Security Lead | W31: 46387 | X31: Open | Y31: Open SoD conflicts; overdue access reviews | Z31: 46273 | AA31: =IF(OR(Z31="",R31=""),"",Z31+INDEX(Scoring!$E$21:$E$24,MATCH(R31,Scoring!$A$21:$A$24,0))) -> 46453 | AB31: =IF(Q31="","",Q31+(1000-ROW())/100000) -> 6.00969
A32: R-027 | B32: 46062 | C32: Cyber: Identity & Access | D32: Service account and API key sprawl with static credentials | E32: Non-human accounts with non-expiring secrets are rarely reviewed, offering attackers stealthy, long-lived access. | F32: Service accounts, API keys, automation | G32: Chief Information Security Officer | H32: 4 | I32: 4 | J32: =IF(OR(H32="",I32=""),"",H32*I32) -> 16 | K32: =IF(J32="","",IF(J32>=Scoring!$B$24,"Critical",IF(J32>=Scoring!$B$23,"High",IF(J32>=Scoring!$B$22,"Medium","Low")))) -> Critical | L32: Service account register (incomplete); some secrets held in a vault. | M32: ISO 27001 A.5.17, A.8.2 | NIST PR.AA | CIS 5 | N32: Weak | O32: 3 | P32: 3 | Q32: =IF(OR(O32="",P32=""),"",O32*P32) -> 9 | R32: =IF(Q32="","",IF(Q32>=Scoring!$B$24,"Critical",IF(Q32>=Scoring!$B$23,"High",IF(Q32>=Scoring!$B$22,"Medium","Low")))) -> Medium | S32: =IF(Q32="","",IF(Q32<=Scoring!$B$27,"Yes","No")) -> Yes | T32: Mitigate | U32: Inventory all service accounts; migrate secrets to vault with automatic rotation. | V32: Platform Security Lead | W32: 46507 | X32: Open | Y32: % service accounts with owner and rotation; secrets older than 365 days | Z32: 46280 | AA32: =IF(OR(Z32="",R32=""),"",Z32+INDEX(Scoring!$E$21:$E$24,MATCH(R32,Scoring!$A$21:$A$24,0))) -> 46460 | AB32: =IF(Q32="","",Q32+(1000-ROW())/100000) -> 9.00968
A33: R-028 | B33: 46067 | C33: Cyber: Identity & Access | D33: Credential stuffing against customer and dealer ordering portal | E33: Attackers reuse stolen passwords at scale against the ordering portal, causing account takeover, fraudulent orders and support costs. | F33: Dealer and customer portal | G33: Chief Digital Officer | H33: 4 | I33: 3 | J33: =IF(OR(H33="",I33=""),"",H33*I33) -> 12 | K33: =IF(J33="","",IF(J33>=Scoring!$B$24,"Critical",IF(J33>=Scoring!$B$23,"High",IF(J33>=Scoring!$B$22,"Medium","Low")))) -> High | L33: WAF with rate limiting; CAPTCHA; breached-password check (planned). | M33: ISO 27001 A.8.5, A.8.20 | NIST PR.AA, DE.CM | OWASP OAT-008 | N33: Adequate | O33: 3 | P33: 2 | Q33: =IF(OR(O33="",P33=""),"",O33*P33) -> 6 | R33: =IF(Q33="","",IF(Q33>=Scoring!$B$24,"Critical",IF(Q33>=Scoring!$B$23,"High",IF(Q33>=Scoring!$B$22,"Medium","Low")))) -> Medium | S33: =IF(Q33="","",IF(Q33<=Scoring!$B$27,"Yes","No")) -> Yes | T33: Mitigate | U33: Enable breached-password screening; offer passkeys and optional MFA for dealers. | V33: Portal Product Owner | W33: 46446 | X33: In Progress | Y33: Credential stuffing attempts blocked per month; account takeover incidents | Z33: 46287 | AA33: =IF(OR(Z33="",R33=""),"",Z33+INDEX(Scoring!$E$21:$E$24,MATCH(R33,Scoring!$A$21:$A$24,0))) -> 46467 | AB33: =IF(Q33="","",Q33+(1000-ROW())/100000) -> 6.00967
A34: R-029 | B34: 46072 | C34: Cyber: Identity & Access | D34: Weak access governance for contractors and temporary staff | E34: Third-party staff often keep access beyond contract end dates, and shared accounts are used on plant sites. | F34: Contractor accounts, plant systems | G34: Chief Operating Officer | H34: 3 | I34: 3 | J34: =IF(OR(H34="",I34=""),"",H34*I34) -> 9 | K34: =IF(J34="","",IF(J34>=Scoring!$B$24,"Critical",IF(J34>=Scoring!$B$23,"High",IF(J34>=Scoring!$B$22,"Medium","Low")))) -> Medium | L34: Contractor sponsor required for access; end dates set inconsistently. | M34: ISO 27001 A.5.16, A.5.18 | NIST PR.AA, GV.SC | N34: Weak | O34: 3 | P34: 2 | Q34: =IF(OR(O34="",P34=""),"",O34*P34) -> 6 | R34: =IF(Q34="","",IF(Q34>=Scoring!$B$24,"Critical",IF(Q34>=Scoring!$B$23,"High",IF(Q34>=Scoring!$B$22,"Medium","Low")))) -> Medium | S34: =IF(Q34="","",IF(Q34<=Scoring!$B$27,"Yes","No")) -> Yes | T34: Mitigate | U34: Mandatory expiry dates on all contractor accounts; ban shared accounts. | V34: Identity & Access Manager | W34: 46418 | X34: Open | Y34: Contractor accounts without expiry; shared accounts in use | Z34: 46294 | AA34: =IF(OR(Z34="",R34=""),"",Z34+INDEX(Scoring!$E$21:$E$24,MATCH(R34,Scoring!$A$21:$A$24,0))) -> 46474 | AB34: =IF(Q34="","",Q34+(1000-ROW())/100000) -> 6.00966
A35: R-030 | B35: 46077 | C35: Cyber: Identity & Access | D35: Session token theft by infostealer malware bypasses MFA | E35: Malware on unmanaged devices steals browser session cookies, letting attackers hijack authenticated sessions to cloud and SaaS apps. | F35: Cloud and SaaS sessions | G35: Chief Information Security Officer | H35: 3 | I35: 4 | J35: =IF(OR(H35="",I35=""),"",H35*I35) -> 12 | K35: =IF(J35="","",IF(J35>=Scoring!$B$24,"Critical",IF(J35>=Scoring!$B$23,"High",IF(J35>=Scoring!$B$22,"Medium","Low")))) -> High | L35: EDR on corporate devices; conditional access with device compliance (partial); short admin session lifetimes. | M35: ISO 27001 A.8.1, A.8.5, A.8.7 | NIST PR.AA, DE.CM | N35: Adequate | O35: 2 | P35: 4 | Q35: =IF(OR(O35="",P35=""),"",O35*P35) -> 8 | R35: =IF(Q35="","",IF(Q35>=Scoring!$B$24,"Critical",IF(Q35>=Scoring!$B$23,"High",IF(Q35>=Scoring!$B$22,"Medium","Low")))) -> Medium | S35: =IF(Q35="","",IF(Q35<=Scoring!$B$27,"Yes","No")) -> Yes | T35: Mitigate | U35: Enforce device-bound sessions; block unmanaged devices from sensitive apps. | V35: Head of End-User Computing | W35: 46538 | X35: Open | Y35: % sensitive app sessions from compliant devices; infostealer detections | Z35: 46301 | AA35: =IF(OR(Z35="",R35=""),"",Z35+INDEX(Scoring!$E$21:$E$24,MATCH(R35,Scoring!$A$21:$A$24,0))) -> 46481 | AB35: =IF(Q35="","",Q35+(1000-ROW())/100000) -> 8.00965
A36: R-031 | B36: 46082 | C36: Cyber: Network & Infrastructure | D36: Unpatched vulnerabilities on internet-facing systems | E36: Slow patching and incomplete asset visibility leave exploitable flaws on public systems, enabling intrusion and data theft. | F36: Web servers, firewalls, VPN | G36: Head of IT Operations | H36: 4 | I36: 4 | J36: =IF(OR(H36="",I36=""),"",H36*I36) -> 16 | K36: =IF(J36="","",IF(J36>=Scoring!$B$24,"Critical",IF(J36>=Scoring!$B$23,"High",IF(J36>=Scoring!$B$22,"Medium","Low")))) -> Critical | L36: Monthly patch cycle; quarterly vulnerability scans. | M36: ISO 27001 A.8.8, A.8.9 | NIST ID.RA, PR.PS | CIS 7 | N36: Weak | O36: 3 | P36: 4 | Q36: =IF(OR(O36="",P36=""),"",O36*P36) -> 12 | R36: =IF(Q36="","",IF(Q36>=Scoring!$B$24,"Critical",IF(Q36>=Scoring!$B$23,"High",IF(Q36>=Scoring!$B$22,"Medium","Low")))) -> High | S36: =IF(Q36="","",IF(Q36<=Scoring!$B$27,"Yes","No")) -> No | T36: Mitigate | U36: Introduce risk-based patch SLAs (critical within 7 days); weekly external scans. | V36: Infrastructure Lead | W36: 46295 | X36: In Progress | Y36: % critical vulns patched in SLA; critical vulns open >30 days | Z36: 46253 | AA36: =IF(OR(Z36="",R36=""),"",Z36+INDEX(Scoring!$E$21:$E$24,MATCH(R36,Scoring!$A$21:$A$24,0))) -> 46343 | AB36: =IF(Q36="","",Q36+(1000-ROW())/100000) -> 12.00964
A37: R-032 | B37: 46087 | C37: Cyber: Network & Infrastructure | D37: Zero-day exploitation of VPN and edge appliances | E37: Attackers increasingly target firewall and VPN appliances with zero-day flaws, gaining a foothold before patches exist. | F37: VPN, firewalls, load balancers | G37: Chief Information Security Officer | H37: 3 | I37: 5 | J37: =IF(OR(H37="",I37=""),"",H37*I37) -> 15 | K37: =IF(J37="","",IF(J37>=Scoring!$B$24,"Critical",IF(J37>=Scoring!$B$23,"High",IF(J37>=Scoring!$B$22,"Medium","Low")))) -> Critical | L37: Vendor advisories monitored; edge device inventory; geo-blocking. | M37: ISO 27001 A.8.8, A.8.20, A.8.21 | NIST ID.RA, PR.IR, DE.CM | N37: Adequate | O37: 3 | P37: 4 | Q37: =IF(OR(O37="",P37=""),"",O37*P37) -> 12 | R37: =IF(Q37="","",IF(Q37>=Scoring!$B$24,"Critical",IF(Q37>=Scoring!$B$23,"High",IF(Q37>=Scoring!$B$22,"Medium","Low")))) -> High | S37: =IF(Q37="","",IF(Q37<=Scoring!$B$27,"Yes","No")) -> No | T37: Mitigate | U37: Adopt zero-trust access to replace legacy VPN; add edge device integrity monitoring. | V37: Head of Network Engineering | W37: 46568 | X37: In Progress | Y37: Time to mitigate edge zero-days (target <48h); % apps behind ZTNA | Z37: 46260 | AA37: =IF(OR(Z37="",R37=""),"",Z37+INDEX(Scoring!$E$21:$E$24,MATCH(R37,Scoring!$A$21:$A$24,0))) -> 46350 | AB37: =IF(Q37="","",Q37+(1000-ROW())/100000) -> 12.00963
A38: R-033 | B38: 46092 | C38: Cyber: Network & Infrastructure | D38: End-of-life operating systems and software in production | E38: Unsupported systems no longer receive security patches, creating permanent exploitable weaknesses. | F38: 6 legacy Windows Server hosts, old database versions | G38: Chief Information Officer | H38: 4 | I38: 4 | J38: =IF(OR(H38="",I38=""),"",H38*I38) -> 16 | K38: =IF(J38="","",IF(J38>=Scoring!$B$24,"Critical",IF(J38>=Scoring!$B$23,"High",IF(J38>=Scoring!$B$22,"Medium","Low")))) -> Critical | L38: EOL assets flagged in inventory; isolated VLAN; extended support for some hosts. | M38: ISO 27001 A.5.9, A.8.8 | NIST ID.AM, PR.PS | CIS 2 | N38: Weak | O38: 3 | P38: 4 | Q38: =IF(OR(O38="",P38=""),"",O38*P38) -> 12 | R38: =IF(Q38="","",IF(Q38>=Scoring!$B$24,"Critical",IF(Q38>=Scoring!$B$23,"High",IF(Q38>=Scoring!$B$22,"Medium","Low")))) -> High | S38: =IF(Q38="","",IF(Q38<=Scoring!$B$27,"Yes","No")) -> No | T38: Avoid | U38: Decommission or migrate EOL systems; apply compensating controls until retired. | V38: Infrastructure Lead | W38: 46477 | X38: In Progress | Y38: EOL systems in production (target 0) | Z38: 46267 | AA38: =IF(OR(Z38="",R38=""),"",Z38+INDEX(Scoring!$E$21:$E$24,MATCH(R38,Scoring!$A$21:$A$24,0))) -> 46357 | AB38: =IF(Q38="","",Q38+(1000-ROW())/100000) -> 12.00962
A39: R-034 | B39: 46097 | C39: Cyber: Network & Infrastructure | D39: Flat network enables lateral movement after initial compromise | E39: Weak segmentation between user, server and plant networks lets an attacker move quickly from one infected device to critical systems. | F39: Corporate and data centre networks | G39: Head of Network Engineering | H39: 4 | I39: 4 | J39: =IF(OR(H39="",I39=""),"",H39*I39) -> 16 | K39: =IF(J39="","",IF(J39>=Scoring!$B$24,"Critical",IF(J39>=Scoring!$B$23,"High",IF(J39>=Scoring!$B$22,"Medium","Low")))) -> Critical | L39: VLANs by function; internal firewalls at data centre edge; limited east-west monitoring. | M39: ISO 27001 A.8.20, A.8.22 | NIST PR.IR | CIS 12 | N39: Adequate | O39: 3 | P39: 3 | Q39: =IF(OR(O39="",P39=""),"",O39*P39) -> 9 | R39: =IF(Q39="","",IF(Q39>=Scoring!$B$24,"Critical",IF(Q39>=Scoring!$B$23,"High",IF(Q39>=Scoring!$B$22,"Medium","Low")))) -> Medium | S39: =IF(Q39="","",IF(Q39<=Scoring!$B$27,"Yes","No")) -> Yes | T39: Mitigate | U39: Implement micro-segmentation for crown-jewel systems; restrict admin protocols between zones. | V39: Network Security Architect | W39: 46538 | X39: In Progress | Y39: % crown-jewel systems micro-segmented; unexpected east-west flows | Z39: 46274 | AA39: =IF(OR(Z39="",R39=""),"",Z39+INDEX(Scoring!$E$21:$E$24,MATCH(R39,Scoring!$A$21:$A$24,0))) -> 46454 | AB39: =IF(Q39="","",Q39+(1000-ROW())/100000) -> 9.00961
... A42: R-037 | B42: 46112 | C42: Cyber: Network & Infrastructure | D42: Rogue devices and insecure wireless at offices and plants | E42: Unmanaged devices or rogue access points could give attackers a path into internal networks, especially at plants with weaker controls. | F42: Wi-Fi, switch ports, plant floor | G42: Head of IT Operations | H42: 3 | I42: 3 | J42: =IF(OR(H42="",I42=""),"",H42*I42) -> 9 | K42: =IF(J42="","",IF(J42>=Scoring!$B$24,"Critical",IF(J42>=Scoring!$B$23,"High",IF(J42>=Scoring!$B$22,"Medium","Low")))) -> Medium | L42: WPA3-Enterprise at HQ; network access control at HQ only. | M42: ISO 27001 A.8.1, A.8.20 | NIST ID.AM, PR.IR | CIS 1, 13 | N42: Adequate | O42: 2 | P42: 3 | Q42: =IF(OR(O42="",P42=""),"",O42*P42) -> 6 | R42: =IF(Q42="","",IF(Q42>=Scoring!$B$24,"Critical",IF(Q42>=Scoring!$B$23,"High",IF(Q42>=Scoring!$B$22,"Medium","Low")))) -> Medium | S42: =IF(Q42="","",IF(Q42<=Scoring!$B$27,"Yes","No")) -> Yes | T42: Mitigate | U42: Extend NAC to plants; scan for rogue access points quarterly. | V42: Network Engineering Lead | W42: 46507 | X42: Open | Y42: Unmanaged devices detected; sites with NAC | Z42: 46295 | AA42: =IF(OR(Z42="",R42=""),"",Z42+INDEX(Scoring!$E$21:$E$24,MATCH(R42,Scoring!$A$21:$A$24,0))) -> 46475 | AB42: =IF(Q42="","",Q42+(1000-ROW())/100000) -> 6.00958
A43: R-038 | B43: 46117 | C43: Cyber: Network & Infrastructure | D43: DNS hijacking, domain expiry or registrar account compromise | E43: Takeover of company domains or DNS records could redirect customers and staff to attacker sites or break email. | F43: Corporate domains, DNS | G43: Head of Network Engineering | H43: 2 | I43: 4 | J43: =IF(OR(H43="",I43=""),"",H43*I43) -> 8 | K43: =IF(J43="","",IF(J43>=Scoring!$B$24,"Critical",IF(J43>=Scoring!$B$23,"High",IF(J43>=Scoring!$B$22,"Medium","Low")))) -> Medium | L43: Registrar lock on primary domains; DNSSEC on main domain; MFA on registrar account. | M43: ISO 27001 A.8.20, A.8.21 | NIST PR.IR, ID.AM | N43: Strong | O43: 1 | P43: 4 | Q43: =IF(OR(O43="",P43=""),"",O43*P43) -> 4 | R43: =IF(Q43="","",IF(Q43>=Scoring!$B$24,"Critical",IF(Q43>=Scoring!$B$23,"High",IF(Q43>=Scoring!$B$22,"Medium","Low")))) -> Low | S43: =IF(Q43="","",IF(Q43<=Scoring!$B$27,"Yes","No")) -> Yes | T43: Accept | U43: Accept residual risk; add expiry alerts and annual domain inventory review. | V43: Network Engineering Lead | X43: Monitoring | Y43: Domains with registry lock; days to nearest expiry | Z43: 46302 | AA43: =IF(OR(Z43="",R43=""),"",Z43+INDEX(Scoring!$E$21:$E$24,MATCH(R43,Scoring!$A$21:$A$24,0))) -> 46667 | AB43: =IF(Q43="","",Q43+(1000-ROW())/100000) -> 4.00957
A44: R-039 | B44: 46122 | C44: Cyber: Data Protection & Privacy | D44: Personal data breach affecting customers or employees | E44: Due to weak access controls or exfiltration, personal data of customers, dealers or staff could be exposed, triggering GDPR notification, fines and litigation. | F44: CRM, HR system, loyalty database | G44: Data Protection Officer | H44: 3 | I44: 5 | J44: =IF(OR(H44="",I44=""),"",H44*I44) -> 15 | K44: =IF(J44="","",IF(J44>=Scoring!$B$24,"Critical",IF(J44>=Scoring!$B$23,"High",IF(J44>=Scoring!$B$22,"Medium","Low")))) -> Critical | L44: ROPA; DPIAs for new processing; encryption at rest; breach notification procedure. | M44: ISO 27001 A.5.34, A.8.24 | ISO 27701 | NIST PR.DS, GV.PO | N44: Adequate | O44: 2 | P44: 4 | Q44: =IF(OR(O44="",P44=""),"",O44*P44) -> 8 | R44: =IF(Q44="","",IF(Q44>=Scoring!$B$24,"Critical",IF(Q44>=Scoring!$B$23,"High",IF(Q44>=Scoring!$B$22,"Medium","Low")))) -> Medium | S44: =IF(Q44="","",IF(Q44<=Scoring!$B$27,"Yes","No")) -> Yes | T44: Mitigate | U44: Refresh ROPA; implement field-level encryption for HR and loyalty data. | V44: Privacy Analyst | W44: 46477 | X44: In Progress | Y44: Personal data incidents per quarter; overdue DPIAs | Z44: 46254 | AA44: =IF(OR(Z44="",R44=""),"",Z44+INDEX(Scoring!$E$21:$E$24,MATCH(R44,Scoring!$A$21:$A$24,0))) -> 46434 | AB44: =IF(Q44="","",Q44+(1000-ROW())/100000) -> 8.00956
A45: R-040 | B45: 46127 | C45: Cyber: Data Protection & Privacy | D45: Unencrypted data on laptops and removable media | E45: Lost or stolen devices could expose locally stored sensitive data and require breach assessment. | F45: Laptops, USB drives | G45: Chief Information Officer | H45: 3 | I45: 3 | J45: =IF(OR(H45="",I45=""),"",H45*I45) -> 9 | K45: =IF(J45="","",IF(J45>=Scoring!$B$24,"Critical",IF(J45>=Scoring!$B$23,"High",IF(J45>=Scoring!$B$22,"Medium","Low")))) -> Medium | L45: Full-disk encryption on all corporate laptops; USB blocked by default; MDM. | M45: ISO 27001 A.7.9, A.8.1, A.8.24 | NIST PR.DS | CIS 3 | N45: Strong | O45: 1 | P45: 2 | Q45: =IF(OR(O45="",P45=""),"",O45*P45) -> 2 | R45: =IF(Q45="","",IF(Q45>=Scoring!$B$24,"Critical",IF(Q45>=Scoring!$B$23,"High",IF(Q45>=Scoring!$B$22,"Medium","Low")))) -> Low | S45: =IF(Q45="","",IF(Q45<=Scoring!$B$27,"Yes","No")) -> Yes | T45: Mitigate | U45: Completed: monitor encryption compliance quarterly. | V45: Endpoint Engineer | W45: 46265 | X45: Closed | Y45: % devices encrypted (target 100%) | Z45: 46261 | AA45: =IF(OR(Z45="",R45=""),"",Z45+INDEX(Scoring!$E$21:$E$24,MATCH(R45,Scoring!$A$21:$A$24,0))) -> 46626 | AB45: =IF(Q45="","",Q45+(1000-ROW())/100000) -> 2.00955
A46: R-041 | B46: 46132 | C46: Cyber: Data Protection & Privacy | D46: Malicious insider exfiltrates sensitive data | E46: An employee or contractor could copy customer, financial or formulation data to personal storage for sale or personal gain. | F46: Customer data, financials, formulations | G46: Chief Information Security Officer | H46: 3 | I46: 4 | J46: =IF(OR(H46="",I46=""),"",H46*I46) -> 12 | K46: =IF(J46="","",IF(J46>=Scoring!$B$24,"Critical",IF(J46>=Scoring!$B$23,"High",IF(J46>=Scoring!$B$22,"Medium","Low")))) -> High | L46: DLP on email and web; privileged access monitoring; HR vetting. | M46: ISO 27001 A.8.12, A.8.16, A.6.1 | NIST PR.DS, DE.CM | N46: Adequate | O46: 2 | P46: 3 | Q46: =IF(OR(O46="",P46=""),"",O46*P46) -> 6 | R46: =IF(Q46="","",IF(Q46>=Scoring!$B$24,"Critical",IF(Q46>=Scoring!$B$23,"High",IF(Q46>=Scoring!$B$22,"Medium","Low")))) -> Medium | S46: =IF(Q46="","",IF(Q46<=Scoring!$B$27,"Yes","No")) -> Yes | T46: Mitigate | U46: Deploy user behaviour analytics; extend DLP to cloud storage. | V46: Head of Security Operations | W46: 46446 | X46: Open | Y46: High-risk DLP alerts; UBA anomalies investigated | Z46: 46268 | AA46: =IF(OR(Z46="",R46=""),"",Z46+INDEX(Scoring!$E$21:$E$24,MATCH(R46,Scoring!$A$21:$A$24,0))) -> 46448 | AB46: =IF(Q46="","",Q46+(1000-ROW())/100000) -> 6.00954
A47: R-042 | B47: 46137 | C47: Cyber: Data Protection & Privacy | D47: Poor data classification and over-retention | E47: Without clear labels and retention rules, sensitive data accumulates in uncontrolled locations, enlarging breach impact and compliance exposure. | F47: File shares, SharePoint, email archives | G47: Head of Data Governance | H47: 4 | I47: 3 | J47: =IF(OR(H47="",I47=""),"",H47*I47) -> 12 | K47: =IF(J47="","",IF(J47>=Scoring!$B$24,"Critical",IF(J47>=Scoring!$B$23,"High",IF(J47>=Scoring!$B$22,"Medium","Low")))) -> High | L47: Classification policy; manual labelling; retention schedule drafted. | M47: ISO 27001 A.5.12, A.5.13, A.8.10 | NIST ID.AM, PR.DS | N47: Weak | O47: 3 | P47: 3 | Q47: =IF(OR(O47="",P47=""),"",O47*P47) -> 9 | R47: =IF(Q47="","",IF(Q47>=Scoring!$B$24,"Critical",IF(Q47>=Scoring!$B$23,"High",IF(Q47>=Scoring!$B$22,"Medium","Low")))) -> Medium | S47: =IF(Q47="","",IF(Q47<=Scoring!$B$27,"Yes","No")) -> Yes | T47: Mitigate | U47: Roll out auto-labelling; enforce retention and deletion on file shares. | V47: Records Manager | W47: 46568 | X47: Open | Y47: % repositories labelled; data past retention (TB) | Z47: 46275 | AA47: =IF(OR(Z47="",R47=""),"",Z47+INDEX(Scoring!$E$21:$E$24,MATCH(R47,Scoring!$A$21:$A$24,0))) -> 46455 | AB47: =IF(Q47="","",Q47+(1000-ROW())/100000) -> 9.00953
A48: R-043 | B48: 46142 | C48: Cyber: Data Protection & Privacy | D48: Non-compliant cross-border personal data transfers | E48: Transfers of personal data between regions without valid legal mechanisms could breach privacy law and lead to orders to stop processing. | F48: Global HR and CRM platforms | G48: General Counsel | H48: 3 | I48: 4 | J48: =IF(OR(H48="",I48=""),"",H48*I48) -> 12 | K48: =IF(J48="","",IF(J48>=Scoring!$B$24,"Critical",IF(J48>=Scoring!$B$23,"High",IF(J48>=Scoring!$B$22,"Medium","Low")))) -> High | L48: Standard contractual clauses; transfer impact assessments for main vendors. | M48: ISO 27001 A.5.31, A.5.34 | ISO 27701 | NIST GV.OC | N48: Adequate | O48: 2 | P48: 3 | Q48: =IF(OR(O48="",P48=""),"",O48*P48) -> 6 | R48: =IF(Q48="","",IF(Q48>=Scoring!$B$24,"Critical",IF(Q48>=Scoring!$B$23,"High",IF(Q48>=Scoring!$B$22,"Medium","Low")))) -> Medium | S48: =IF(Q48="","",IF(Q48<=Scoring!$B$27,"Yes","No")) -> Yes | T48: Mitigate | U48: Complete transfer impact assessments for all vendors; map data flows. | V48: Privacy Counsel | W48: 46418 | X48: In Progress | Y48: % vendors with completed transfer assessment | Z48: 46282 | AA48: =IF(OR(Z48="",R48=""),"",Z48+INDEX(Scoring!$E$21:$E$24,MATCH(R48,Scoring!$A$21:$A$24,0))) -> 46462 | AB48: =IF(Q48="","",Q48+(1000-ROW())/100000) -> 6.00952
A49: R-044 | B49: 46147 | C49: Cyber: Data Protection & Privacy | D49: Departing employees take trade secrets and formulations | E49: Staff leaving for competitors could take recipes, supplier terms or R&D data, causing loss of competitive advantage. | F49: Recipes, R&D files | G49: Chief People Officer | H49: 3 | I49: 4 | J49: =IF(OR(H49="",I49=""),"",H49*I49) -> 12 | K49: =IF(J49="","",IF(J49>=Scoring!$B$24,"Critical",IF(J49>=Scoring!$B$23,"High",IF(J49>=Scoring!$B$22,"Medium","Low")))) -> High | L49: NDAs; offboarding checklist; DLP monitoring on R&D share. | M49: ISO 27001 A.6.5, A.6.6, A.8.12 | NIST PR.DS | N49: Adequate | O49: 2 | P49: 3 | Q49: =IF(OR(O49="",P49=""),"",O49*P49) -> 6 | R49: =IF(Q49="","",IF(Q49>=Scoring!$B$24,"Critical",IF(Q49>=Scoring!$B$23,"High",IF(Q49>=Scoring!$B$22,"Medium","Low")))) -> Medium | S49: =IF(Q49="","",IF(Q49<=Scoring!$B$27,"Yes","No")) -> Yes | T49: Mitigate | U49: Review data activity of leavers; restrict bulk download from R&D repositories. | V49: Head of R&D Operations | W49: 46446 | X49: Open | Y49: Bulk downloads by leavers; NDAs signed (target 100%) | Z49: 46289 | AA49: =IF(OR(Z49="",R49=""),"",Z49+INDEX(Scoring!$E$21:$E$24,MATCH(R49,Scoring!$A$21:$A$24,0))) -> 46469 | AB49: =IF(Q49="","",Q49+(1000-ROW())/100000) -> 6.00951
A50: R-045 | B50: 46152 | C50: Cyber: Data Protection & Privacy | D50: Backup failure or inability to restore after an attack | E50: Untested or compromised backups may be unusable when needed, prolonging recovery from ransomware or data corruption. | F50: Backup platform, ERP, databases | G50: Head of IT Operations | H50: 3 | I50: 5 | J50: =IF(OR(H50="",I50=""),"",H50*I50) -> 15 | K50: =IF(J50="","",IF(J50>=Scoring!$B$24,"Critical",IF(J50>=Scoring!$B$23,"High",IF(J50>=Scoring!$B$22,"Medium","Low")))) -> Critical | L50: Daily encrypted backups; failed-job alerts; ad hoc restore tests. | M50: ISO 27001 A.8.13, A.8.14 | NIST PR.DS, RC.RP | CIS 11 | N50: Weak | O50: 3 | P50: 4 | Q50: =IF(OR(O50="",P50=""),"",O50*P50) -> 12 | R50: =IF(Q50="","",IF(Q50>=Scoring!$B$24,"Critical",IF(Q50>=Scoring!$B$23,"High",IF(Q50>=Scoring!$B$22,"Medium","Low")))) -> High | S50: =IF(Q50="","",IF(Q50<=Scoring!$B$27,"Yes","No")) -> No | T50: Mitigate | U50: Run quarterly restore tests of tier-1 systems; keep immutable copy in a separate account. | V50: Infrastructure Lead | W50: 46387 | X50: In Progress | Y50: Backup success rate (target >=99%); restore test pass rate | Z50: 46296 | AA50: =IF(OR(Z50="",R50=""),"",Z50+INDEX(Scoring!$E$21:$E$24,MATCH(R50,Scoring!$A$21:$A$24,0))) -> 46386 | AB50: =IF(Q50="","",Q50+(1000-ROW())/100000) -> 12.0095
A51: R-046 | B51: 46157 | C51: Cyber: Data Protection & Privacy | D51: Misdirected emails and over-shared links expose data | E51: Everyday mistakes such as wrong recipients or open sharing links can expose confidential data externally. | F51: Email, collaboration tools | G51: Head of Data Governance | H51: 5 | I51: 2 | J51: =IF(OR(H51="",I51=""),"",H51*I51) -> 10 | K51: =IF(J51="","",IF(J51>=Scoring!$B$24,"Critical",IF(J51>=Scoring!$B$23,"High",IF(J51>=Scoring!$B$22,"Medium","Low")))) -> High | L51: Awareness training; external recipient warnings; link expiry (partial). | M51: ISO 27001 A.5.14, A.8.12, A.6.3 | NIST PR.DS, PR.AT | N51: Adequate | O51: 4 | P51: 2 | Q51: =IF(OR(O51="",P51=""),"",O51*P51) -> 8 | R51: =IF(Q51="","",IF(Q51>=Scoring!$B$24,"Critical",IF(Q51>=Scoring!$B$23,"High",IF(Q51>=Scoring!$B$22,"Medium","Low")))) -> Medium | S51: =IF(Q51="","",IF(Q51<=Scoring!$B$27,"Yes","No")) -> Yes | T51: Mitigate | U51: Enable DLP policies for external sharing; default links to internal-only. | V51: Collaboration Platform Lead | W51: 46371 | X51: In Progress | Y51: External share incidents; % links with expiry | Z51: 46303 | AA51: =IF(OR(Z51="",R51=""),"",Z51+INDEX(Scoring!$E$21:$E$24,MATCH(R51,Scoring!$A$21:$A$24,0))) -> 46483 | AB51: =IF(Q51="","",Q51+(1000-ROW())/100000) -> 8.00949
A52: R-047 | B52: 46162 | C52: Cyber: Application & Cloud | D52: Misconfigured cloud storage exposes sensitive data | E52: Manual configuration errors or excessive permissions could expose storage or databases publicly, causing a data breach and notification duties. | F52: Cloud storage, databases | G52: Head of Cloud Platform | H52: 3 | I52: 5 | J52: =IF(OR(H52="",I52=""),"",H52*I52) -> 15 | K52: =IF(J52="","",IF(J52>=Scoring!$B$24,"Critical",IF(J52>=Scoring!$B$23,"High",IF(J52>=Scoring!$B$22,"Medium","Low")))) -> Critical | L52: Infrastructure-as-code with peer review; CSPM alerts; default-deny storage policy. | M52: ISO 27001 A.5.23, A.8.9 | NIST PR.PS, ID.RA | CIS 4 | N52: Adequate | O52: 2 | P52: 4 | Q52: =IF(OR(O52="",P52=""),"",O52*P52) -> 8 | R52: =IF(Q52="","",IF(Q52>=Scoring!$B$24,"Critical",IF(Q52>=Scoring!$B$23,"High",IF(Q52>=Scoring!$B$22,"Medium","Low")))) -> Medium | S52: =IF(Q52="","",IF(Q52<=Scoring!$B$27,"Yes","No")) -> Yes | T52: Mitigate | U52: Enforce policy-as-code guardrails; auto-remediate public storage. | V52: Cloud Security Engineer | W52: 46371 | X52: In Progress | Y52: Public storage resources (target 0); CSPM high findings >14 days | Z52: 46255 | AA52: =IF(OR(Z52="",R52=""),"",Z52+INDEX(Scoring!$E$21:$E$24,MATCH(R52,Scoring!$A$21:$A$24,0))) -> 46435 | AB52: =IF(Q52="","",Q52+(1000-ROW())/100000) -> 8.00948
A53: R-048 | B53: 46167 | C53: Cyber: Application & Cloud | D53: Insecure code in internally developed applications | E53: Gaps in secure development practice could ship exploitable flaws to production in customer-facing apps. | F53: Customer web and mobile apps | G53: Head of Engineering | H53: 3 | I53: 4 | J53: =IF(OR(H53="",I53=""),"",H53*I53) -> 12 | K53: =IF(J53="","",IF(J53>=Scoring!$B$24,"Critical",IF(J53>=Scoring!$B$23,"High",IF(J53>=Scoring!$B$22,"Medium","Low")))) -> High | L53: SAST in CI; mandatory peer review; annual penetration test. | M53: ISO 27001 A.8.25, A.8.28, A.8.29 | NIST PR.PS | OWASP ASVS | N53: Adequate | O53: 2 | P53: 3 | Q53: =IF(OR(O53="",P53=""),"",O53*P53) -> 6 | R53: =IF(Q53="","",IF(Q53>=Scoring!$B$24,"Critical",IF(Q53>=Scoring!$B$23,"High",IF(Q53>=Scoring!$B$22,"Medium","Low")))) -> Medium | S53: =IF(Q53="","",IF(Q53<=Scoring!$B$27,"Yes","No")) -> Yes | T53: Mitigate | U53: Add DAST to staging; secure coding training for all developers. | V53: DevSecOps Lead | W53: 46418 | X53: In Progress | Y53: Critical code vulns >30 days; % repos with SAST | Z53: 46262 | AA53: =IF(OR(Z53="",R53=""),"",Z53+INDEX(Scoring!$E$21:$E$24,MATCH(R53,Scoring!$A$21:$A$24,0))) -> 46442 | AB53: =IF(Q53="","",Q53+(1000-ROW())/100000) -> 6.00947
A54: R-049 | B54: 46172 | C54: Cyber: Application & Cloud | D54: Vulnerable open-source dependencies and software supply chain | E54: Third-party libraries and build tooling can contain known flaws or be maliciously tampered with, compromising applications and pipelines. | F54: CI/CD pipelines, code repositories | G54: Head of Engineering | H54: 4 | I54: 4 | J54: =IF(OR(H54="",I54=""),"",H54*I54) -> 16 | K54: =IF(J54="","",IF(J54>=Scoring!$B$24,"Critical",IF(J54>=Scoring!$B$23,"High",IF(J54>=Scoring!$B$22,"Medium","Low")))) -> Critical | L54: Dependency scan on main branch; private package mirror (partial). | M54: ISO 27001 A.8.25, A.8.30 | NIST GV.SC, PR.PS | SLSA | N54: Weak | O54: 3 | P54: 4 | Q54: =IF(OR(O54="",P54=""),"",O54*P54) -> 12 | R54: =IF(Q54="","",IF(Q54>=Scoring!$B$24,"Critical",IF(Q54>=Scoring!$B$23,"High",IF(Q54>=Scoring!$B$22,"Medium","Low")))) -> High | S54: =IF(Q54="","",IF(Q54<=Scoring!$B$27,"Yes","No")) -> No | T54: Mitigate | U54: Generate SBOMs; enforce signed builds; block packages with critical CVEs. | V54: DevSecOps Lead | W54: 46507 | X54: Open | Y54: Critical vulnerable dependencies; % builds with SBOM | Z54: 46269 | AA54: =IF(OR(Z54="",R54=""),"",Z54+INDEX(Scoring!$E$21:$E$24,MATCH(R54,Scoring!$A$21:$A$24,0))) -> 46359 | AB54: =IF(Q54="","",Q54+(1000-ROW())/100000) -> 12.00946
A55: R-050 | B55: 46177 | C55: Cyber: Application & Cloud | D55: Secrets and API keys hardcoded in code repositories | E55: Credentials committed to source code can be found by attackers and used to access cloud and internal services. | F55: Source code repositories | G55: Head of Engineering | H55: 4 | I55: 4 | J55: =IF(OR(H55="",I55=""),"",H55*I55) -> 16 | K55: =IF(J55="","",IF(J55>=Scoring!$B$24,"Critical",IF(J55>=Scoring!$B$23,"High",IF(J55>=Scoring!$B$22,"Medium","Low")))) -> Critical | L55: Pre-commit secret scanning (opt-in); vault for new apps. | M55: ISO 27001 A.8.4, A.8.24, A.5.17 | NIST PR.AA, PR.DS | N55: Weak | O55: 3 | P55: 3 | Q55: =IF(OR(O55="",P55=""),"",O55*P55) -> 9 | R55: =IF(Q55="","",IF(Q55>=Scoring!$B$24,"Critical",IF(Q55>=Scoring!$B$23,"High",IF(Q55>=Scoring!$B$22,"Medium","Low")))) -> Medium | S55: =IF(Q55="","",IF(Q55<=Scoring!$B$27,"Yes","No")) -> Yes | T55: Mitigate | U55: Enforce secret scanning org-wide; rotate all exposed keys; purge history. | V55: DevSecOps Lead | W55: 46305 | X55: In Progress | Y55: Active secrets in repos (target 0); mean time to revoke | Z55: 46276 | AA55: =IF(OR(Z55="",R55=""),"",Z55+INDEX(Scoring!$E$21:$E$24,MATCH(R55,Scoring!$A$21:$A$24,0))) -> 46456 | AB55: =IF(Q55="","",Q55+(1000-ROW())/100000) -> 9.00945
... A57: R-052 | B57: 46187 | C57: Cyber: Application & Cloud | D57: Cloud IAM over-permissioning enables privilege escalation | E57: Excessive cloud roles let a compromised identity reach far more resources than needed. | F57: Cloud accounts and roles | G57: Head of Cloud Platform | H57: 4 | I57: 4 | J57: =IF(OR(H57="",I57=""),"",H57*I57) -> 16 | K57: =IF(J57="","",IF(J57>=Scoring!$B$24,"Critical",IF(J57>=Scoring!$B$23,"High",IF(J57>=Scoring!$B$22,"Medium","Low")))) -> Critical | L57: Role templates; quarterly review of admin roles; CIEM trial. | M57: ISO 27001 A.5.15, A.8.2 | NIST PR.AA | CIS 5, 6 | N57: Adequate | O57: 3 | P57: 3 | Q57: =IF(OR(O57="",P57=""),"",O57*P57) -> 9 | R57: =IF(Q57="","",IF(Q57>=Scoring!$B$24,"Critical",IF(Q57>=Scoring!$B$23,"High",IF(Q57>=Scoring!$B$22,"Medium","Low")))) -> Medium | S57: =IF(Q57="","",IF(Q57<=Scoring!$B$27,"Yes","No")) -> Yes | T57: Mitigate | U57: Adopt least-privilege roles through CIEM; remove unused permissions. | V57: Cloud Security Engineer | W57: 46477 | X57: In Progress | Y57: Unused permissions; identities with admin rights | Z57: 46290 | AA57: =IF(OR(Z57="",R57=""),"",Z57+INDEX(Scoring!$E$21:$E$24,MATCH(R57,Scoring!$A$21:$A$24,0))) -> 46470 | AB57: =IF(Q57="","",Q57+(1000-ROW())/100000) -> 9.00943
A58: R-053 | B58: 46192 | C58: Cyber: Application & Cloud | D58: Shadow IT and unapproved SaaS usage | E58: Staff may store company data in unvetted tools, creating unmanaged data copies and unknown vendor risk. | F58: SaaS applications, company data | G58: Chief Information Officer | H58: 4 | I58: 3 | J58: =IF(OR(H58="",I58=""),"",H58*I58) -> 12 | K58: =IF(J58="","",IF(J58>=Scoring!$B$24,"Critical",IF(J58>=Scoring!$B$23,"High",IF(J58>=Scoring!$B$22,"Medium","Low")))) -> High | L58: Approved software catalogue; web proxy; partial SaaS discovery. | M58: ISO 27001 A.5.9, A.5.10, A.5.23 | NIST ID.AM, GV.SC | N58: Adequate | O58: 3 | P58: 2 | Q58: =IF(OR(O58="",P58=""),"",O58*P58) -> 6 | R58: =IF(Q58="","",IF(Q58>=Scoring!$B$24,"Critical",IF(Q58>=Scoring!$B$23,"High",IF(Q58>=Scoring!$B$22,"Medium","Low")))) -> Medium | S58: =IF(Q58="","",IF(Q58<=Scoring!$B$27,"Yes","No")) -> Yes | T58: Accept | U58: Accept residual risk; review SaaS discovery quarterly and onboard high-use tools. | V58: IT Service Manager | X58: Monitoring | Y58: Unapproved apps holding company data | Z58: 46297 | AA58: =IF(OR(Z58="",R58=""),"",Z58+INDEX(Scoring!$E$21:$E$24,MATCH(R58,Scoring!$A$21:$A$24,0))) -> 46477 | AB58: =IF(Q58="","",Q58+(1000-ROW())/100000) -> 6.00942
A59: R-054 | B59: 46197 | C59: Cyber: Application & Cloud | D59: Compromise of the collaboration and email tenant | E59: An attacker controlling the Microsoft 365 tenant could read email, create forwarding rules and spread phishing internally. | F59: Microsoft 365 tenant | G59: Chief Information Security Officer | H59: 3 | I59: 4 | J59: =IF(OR(H59="",I59=""),"",H59*I59) -> 12 | K59: =IF(J59="","",IF(J59>=Scoring!$B$24,"Critical",IF(J59>=Scoring!$B$23,"High",IF(J59>=Scoring!$B$22,"Medium","Low")))) -> High | L59: Baseline security configuration; conditional access; audit logging; Secure Score tracking. | M59: ISO 27001 A.8.9, A.8.15, A.8.5 | NIST PR.PS, PR.AA, DE.CM | N59: Adequate | O59: 2 | P59: 3 | Q59: =IF(OR(O59="",P59=""),"",O59*P59) -> 6 | R59: =IF(Q59="","",IF(Q59>=Scoring!$B$24,"Critical",IF(Q59>=Scoring!$B$23,"High",IF(Q59>=Scoring!$B$22,"Medium","Low")))) -> Medium | S59: =IF(Q59="","",IF(Q59<=Scoring!$B$27,"Yes","No")) -> Yes | T59: Mitigate | U59: Disable legacy authentication; alert on mailbox rules and risky OAuth consent. | V59: Collaboration Platform Lead | W59: 46402 | X59: In Progress | Y59: Secure Score; risky OAuth apps | Z59: 46304 | AA59: =IF(OR(Z59="",R59=""),"",Z59+INDEX(Scoring!$E$21:$E$24,MATCH(R59,Scoring!$A$21:$A$24,0))) -> 46484 | AB59: =IF(Q59="","",Q59+(1000-ROW())/100000) -> 6.00941
A60: R-055 | B60: 46202 | C60: Cyber: Application & Cloud | D60: Uncontrolled changes cause outages and security gaps | E60: Unreviewed changes to production systems could introduce vulnerabilities or cause outages. | F60: Production systems | G60: Chief Information Officer | H60: 3 | I60: 3 | J60: =IF(OR(H60="",I60=""),"",H60*I60) -> 9 | K60: =IF(J60="","",IF(J60>=Scoring!$B$24,"Critical",IF(J60>=Scoring!$B$23,"High",IF(J60>=Scoring!$B$22,"Medium","Low")))) -> Medium | L60: Change advisory board; standard change templates; rollback plans. | M60: ISO 27001 A.8.32, A.8.31 | NIST PR.PS | N60: Strong | O60: 1 | P60: 2 | Q60: =IF(OR(O60="",P60=""),"",O60*P60) -> 2 | R60: =IF(Q60="","",IF(Q60>=Scoring!$B$24,"Critical",IF(Q60>=Scoring!$B$23,"High",IF(Q60>=Scoring!$B$22,"Medium","Low")))) -> Low | S60: =IF(Q60="","",IF(Q60<=Scoring!$B$27,"Yes","No")) -> Yes | T60: Mitigate | U60: Completed: monitor change failure rate. | V60: Change Manager | W60: 46265 | X60: Closed | Y60: Change failure rate (target <5%) | Z60: 46256 | AA60: =IF(OR(Z60="",R60=""),"",Z60+INDEX(Scoring!$E$21:$E$24,MATCH(R60,Scoring!$A$21:$A$24,0))) -> 46621 | AB60: =IF(Q60="","",Q60+(1000-ROW())/100000) -> 2.0094
A61: R-056 | B61: 46207 | C61: Cyber: Application & Cloud | D61: Container and Kubernetes misconfiguration | E61: Insecure cluster settings or vulnerable images could allow container escape or lateral movement in the cloud. | F61: Container platform | G61: Head of Cloud Platform | H61: 3 | I61: 4 | J61: =IF(OR(H61="",I61=""),"",H61*I61) -> 12 | K61: =IF(J61="","",IF(J61>=Scoring!$B$24,"Critical",IF(J61>=Scoring!$B$23,"High",IF(J61>=Scoring!$B$22,"Medium","Low")))) -> High | L61: Image scanning in registry; baseline cluster policies; limited runtime monitoring. | M61: ISO 27001 A.8.9, A.8.27 | NIST PR.PS, DE.CM | CIS Kubernetes Benchmark | N61: Adequate | O61: 2 | P61: 3 | Q61: =IF(OR(O61="",P61=""),"",O61*P61) -> 6 | R61: =IF(Q61="","",IF(Q61>=Scoring!$B$24,"Critical",IF(Q61>=Scoring!$B$23,"High",IF(Q61>=Scoring!$B$22,"Medium","Low")))) -> Medium | S61: =IF(Q61="","",IF(Q61<=Scoring!$B$27,"Yes","No")) -> Yes | T61: Mitigate | U61: Enforce admission control policies; add runtime threat detection. | V61: Platform Engineering Lead | W61: 46477 | X61: Open | Y61: Clusters failing CIS benchmark; critical image vulns | Z61: 46263 | AA61: =IF(OR(Z61="",R61=""),"",Z61+INDEX(Scoring!$E$21:$E$24,MATCH(R61,Scoring!$A$21:$A$24,0))) -> 46443 | AB61: =IF(Q61="","",Q61+(1000-ROW())/100000) -> 6.00939
A62: R-057 | B62: 46212 | C62: Cyber: Threat & Incident Response | D62: Inadequate logging and monitoring delays detection | E62: Log coverage gaps and business-hours-only monitoring mean intrusions may go undetected, increasing breach scope and cost. | F62: SIEM, cloud and SaaS logs | G62: Chief Information Security Officer | H62: 3 | I62: 4 | J62: =IF(OR(H62="",I62=""),"",H62*I62) -> 12 | K62: =IF(J62="","",IF(J62>=Scoring!$B$24,"Critical",IF(J62>=Scoring!$B$23,"High",IF(J62>=Scoring!$B$22,"Medium","Low")))) -> High | L62: Central log collection for servers; SIEM with baseline use cases; business-hours monitoring. | M62: ISO 27001 A.8.15, A.8.16 | NIST DE.CM, DE.AE | CIS 8 | N62: Weak | O62: 3 | P62: 3 | Q62: =IF(OR(O62="",P62=""),"",O62*P62) -> 9 | R62: =IF(Q62="","",IF(Q62>=Scoring!$B$24,"Critical",IF(Q62>=Scoring!$B$23,"High",IF(Q62>=Scoring!$B$22,"Medium","Low")))) -> Medium | S62: =IF(Q62="","",IF(Q62<=Scoring!$B$27,"Yes","No")) -> Yes | T62: Mitigate | U62: Onboard cloud and SaaS logs; engage MDR provider for 24x7 coverage. | V62: Head of Security Operations | W62: 46507 | X62: Open | Y62: Mean time to detect; % critical assets sending logs | Z62: 46270 | AA62: =IF(OR(Z62="",R62=""),"",Z62+INDEX(Scoring!$E$21:$E$24,MATCH(R62,Scoring!$A$21:$A$24,0))) -> 46450 | AB62: =IF(Q62="","",Q62+(1000-ROW())/100000) -> 9.00938
A63: R-058 | B63: 46217 | C63: Cyber: Threat & Incident Response | D63: Immature incident response capability | E63: Infrequent exercises and unclear roles could make the response to a major incident slow or uncoordinated. | F63: Incident response process | G63: Chief Information Security Officer | H63: 3 | I63: 4 | J63: =IF(OR(H63="",I63=""),"",H63*I63) -> 12 | K63: =IF(J63="","",IF(J63>=Scoring!$B$24,"Critical",IF(J63>=Scoring!$B$23,"High",IF(J63>=Scoring!$B$22,"Medium","Low")))) -> High | L63: Incident response plan; on-call roster; IR retainer with external firm. | M63: ISO 27001 A.5.24, A.5.25, A.5.26 | NIST RS.MA, RS.CO | N63: Adequate | O63: 2 | P63: 3 | Q63: =IF(OR(O63="",P63=""),"",O63*P63) -> 6 | R63: =IF(Q63="","",IF(Q63>=Scoring!$B$24,"Critical",IF(Q63>=Scoring!$B$23,"High",IF(Q63>=Scoring!$B$22,"Medium","Low")))) -> Medium | S63: =IF(Q63="","",IF(Q63<=Scoring!$B$27,"Yes","No")) -> Yes | T63: Mitigate | U63: Hold biannual executive tabletop exercises; update communications playbooks. | V63: Incident Response Lead | W63: 46371 | X63: Open | Y63: Exercises completed vs planned; time to declare incident | Z63: 46277 | AA63: =IF(OR(Z63="",R63=""),"",Z63+INDEX(Scoring!$E$21:$E$24,MATCH(R63,Scoring!$A$21:$A$24,0))) -> 46457 | AB63: =IF(Q63="","",Q63+(1000-ROW())/100000) -> 6.00937
A64: R-059 | B64: 46222 | C64: Cyber: Threat & Incident Response | D64: Business email compromise targeting finance | E64: Attackers impersonating suppliers or executives could trick finance staff into paying fraudulent invoices. | F64: Email, accounts payable | G64: Chief Financial Officer | H64: 4 | I64: 4 | J64: =IF(OR(H64="",I64=""),"",H64*I64) -> 16 | K64: =IF(J64="","",IF(J64>=Scoring!$B$24,"Critical",IF(J64>=Scoring!$B$23,"High",IF(J64>=Scoring!$B$22,"Medium","Low")))) -> Critical | L64: Email filtering; call-back verification for bank changes; dual approval over $50k. | M64: ISO 27001 A.5.14, A.6.3 | NIST PR.AT, DE.CM | N64: Adequate | O64: 3 | P64: 3 | Q64: =IF(OR(O64="",P64=""),"",O64*P64) -> 9 | R64: =IF(Q64="","",IF(Q64>=Scoring!$B$24,"Critical",IF(Q64>=Scoring!$B$23,"High",IF(Q64>=Scoring!$B$22,"Medium","Low")))) -> Medium | S64: =IF(Q64="","",IF(Q64<=Scoring!$B$27,"Yes","No")) -> Yes | T64: Mitigate | U64: Add external-sender banners and lookalike domain monitoring; run finance fraud drills. | V64: Treasury Controller | W64: 46387 | X64: In Progress | Y64: BEC attempts blocked; payments held for verification | Z64: 46284 | AA64: =IF(OR(Z64="",R64=""),"",Z64+INDEX(Scoring!$E$21:$E$24,MATCH(R64,Scoring!$A$21:$A$24,0))) -> 46464 | AB64: =IF(Q64="","",Q64+(1000-ROW())/100000) -> 9.00936
A65: R-060 | B65: 46227 | C65: Cyber: Threat & Incident Response | D65: Insider sabotage by a disgruntled employee or administrator | E65: A privileged insider could delete data or disrupt systems in retaliation, causing outage and recovery cost. | F65: Production systems, admin consoles | G65: Chief People Officer | H65: 2 | I65: 4 | J65: =IF(OR(H65="",I65=""),"",H65*I65) -> 8 | K65: =IF(J65="","",IF(J65>=Scoring!$B$24,"Critical",IF(J65>=Scoring!$B$23,"High",IF(J65>=Scoring!$B$22,"Medium","Low")))) -> Medium | L65: Background checks; access logging; four-eyes approval on destructive actions. | M65: ISO 27001 A.6.1, A.8.2, A.8.15 | NIST PR.AA, DE.CM | N65: Adequate | O65: 1 | P65: 4 | Q65: =IF(OR(O65="",P65=""),"",O65*P65) -> 4 | R65: =IF(Q65="","",IF(Q65>=Scoring!$B$24,"Critical",IF(Q65>=Scoring!$B$23,"High",IF(Q65>=Scoring!$B$22,"Medium","Low")))) -> Low | S65: =IF(Q65="","",IF(Q65<=Scoring!$B$27,"Yes","No")) -> Yes | T65: Mitigate | U65: Add alerts for mass deletions; HR trigger for high-risk exits. | V65: Head of Security Operations | W65: 46477 | X65: Monitoring | Y65: Privileged destructive actions without approval | Z65: 46291 | AA65: =IF(OR(Z65="",R65=""),"",Z65+INDEX(Scoring!$E$21:$E$24,MATCH(R65,Scoring!$A$21:$A$24,0))) -> 46656 | AB65: =IF(Q65="","",Q65+(1000-ROW())/100000) -> 4.00935
A66: R-061 | B66: 46232 | C66: Cyber: Threat & Incident Response | D66: Ransomware attack on corporate IT systems | E66: Ransomware could encrypt ERP, file servers and endpoints, with double extortion threatening to publish stolen data. | F66: ERP, file servers, endpoints | G66: Chief Information Security Officer | H66: 4 | I66: 5 | J66: =IF(OR(H66="",I66=""),"",H66*I66) -> 20 | K66: =IF(J66="","",IF(J66>=Scoring!$B$24,"Critical",IF(J66>=Scoring!$B$23,"High",IF(J66>=Scoring!$B$22,"Medium","Low")))) -> Critical | L66: EDR on endpoints; email filtering; offline backups (not fully tested); incident response plan. | M66: ISO 27001 A.8.7, A.8.13, A.5.24 | NIST PR.PS, RS.MA, RC.RP | CIS 10, 11 | N66: Weak | O66: 3 | P66: 5 | Q66: =IF(OR(O66="",P66=""),"",O66*P66) -> 15 | R66: =IF(Q66="","",IF(Q66>=Scoring!$B$24,"Critical",IF(Q66>=Scoring!$B$23,"High",IF(Q66>=Scoring!$B$22,"Medium","Low")))) -> Critical | S66: =IF(Q66="","",IF(Q66<=Scoring!$B$27,"Yes","No")) -> No | T66: Mitigate | U66: Deploy immutable backups; extend EDR to 100%; run ransomware tabletop; agree IR and forensics retainer. | V66: Head of IT Operations | W66: 46477 | X66: In Progress | Y66: % endpoints with EDR; recovery time in restore test vs RTO | Z66: 46298 | AA66: =IF(OR(Z66="",R66=""),"",Z66+INDEX(Scoring!$E$21:$E$24,MATCH(R66,Scoring!$A$21:$A$24,0))) -> 46328 | AB66: =IF(Q66="","",Q66+(1000-ROW())/100000) -> 15.00934
A67: R-062 | B67: 46237 | C67: Cyber: Threat & Incident Response | D67: Advanced persistent threat targeting trade secrets | E67: A well-resourced actor could quietly steal formulations and strategic plans over months. | F67: R&D data, strategic plans | G67: Chief Information Security Officer | H67: 2 | I67: 5 | J67: =IF(OR(H67="",I67=""),"",H67*I67) -> 10 | K67: =IF(J67="","",IF(J67>=Scoring!$B$24,"Critical",IF(J67>=Scoring!$B$23,"High",IF(J67>=Scoring!$B$22,"Medium","Low")))) -> High | L67: Network monitoring on R&D segment; access restrictions; threat briefings. | M67: ISO 27001 A.5.7, A.8.16 | NIST ID.RA, DE.AE | N67: Adequate | O67: 2 | P67: 4 | Q67: =IF(OR(O67="",P67=""),"",O67*P67) -> 8 | R67: =IF(Q67="","",IF(Q67>=Scoring!$B$24,"Critical",IF(Q67>=Scoring!$B$23,"High",IF(Q67>=Scoring!$B$22,"Medium","Low")))) -> Medium | S67: =IF(Q67="","",IF(Q67<=Scoring!$B$27,"Yes","No")) -> Yes | T67: Mitigate | U67: Run quarterly threat hunting; join industry information-sharing group. | V67: Threat Intelligence Lead | W67: 46538 | X67: Open | Y67: Hunt findings per quarter; indicators ingested | Z67: 46305 | AA67: =IF(OR(Z67="",R67=""),"",Z67+INDEX(Scoring!$E$21:$E$24,MATCH(R67,Scoring!$A$21:$A$24,0))) -> 46485 | AB67: =IF(Q67="","",Q67+(1000-ROW())/100000) -> 8.00933
A68: R-063 | B68: 46242 | C68: Cyber: Threat & Incident Response | D68: Threat intelligence not integrated into detection | E68: Without usable threat intelligence, new attacker techniques may be missed by monitoring tools. | F68: SOC tooling | G68: Head of Security Operations | H68: 3 | I68: 3 | J68: =IF(OR(H68="",I68=""),"",H68*I68) -> 9 | K68: =IF(J68="","",IF(J68>=Scoring!$B$24,"Critical",IF(J68>=Scoring!$B$23,"High",IF(J68>=Scoring!$B$22,"Medium","Low")))) -> Medium | L68: Vendor threat feeds into SIEM; ad hoc advisories. | M68: ISO 27001 A.5.7 | NIST ID.RA, DE.AE | N68: Adequate | O68: 2 | P68: 2 | Q68: =IF(OR(O68="",P68=""),"",O68*P68) -> 4 | R68: =IF(Q68="","",IF(Q68>=Scoring!$B$24,"Critical",IF(Q68>=Scoring!$B$23,"High",IF(Q68>=Scoring!$B$22,"Medium","Low")))) -> Low | S68: =IF(Q68="","",IF(Q68<=Scoring!$B$27,"Yes","No")) -> Yes | T68: Mitigate | U68: Automate indicator ingestion; map detections to MITRE ATT&CK. | V68: Threat Intelligence Lead | W68: 46356 | X68: In Progress | Y68: % detections mapped to ATT&CK; indicators matched | Z68: 46257 | AA68: =IF(OR(Z68="",R68=""),"",Z68+INDEX(Scoring!$E$21:$E$24,MATCH(R68,Scoring!$A$21:$A$24,0))) -> 46622 | AB68: =IF(Q68="","",Q68+(1000-ROW())/100000) -> 4.00932
A69: R-064 | B69: 46247 | C69: Cyber: Threat & Incident Response | D69: Failure to meet regulatory breach notification deadlines | E69: Delays in assessing and reporting a breach could breach legal deadlines (e.g. 72 hours under GDPR) and add penalties. | F69: Incident and legal processes | G69: General Counsel | H69: 3 | I69: 4 | J69: =IF(OR(H69="",I69=""),"",H69*I69) -> 12 | K69: =IF(J69="","",IF(J69>=Scoring!$B$24,"Critical",IF(J69>=Scoring!$B$23,"High",IF(J69>=Scoring!$B$22,"Medium","Low")))) -> High | L69: Breach notification procedure; legal on call; regulator contact list. | M69: ISO 27001 A.5.24, A.5.31, A.5.34 | NIST RS.CO, GV.OC | N69: Adequate | O69: 2 | P69: 3 | Q69: =IF(OR(O69="",P69=""),"",O69*P69) -> 6 | R69: =IF(Q69="","",IF(Q69>=Scoring!$B$24,"Critical",IF(Q69>=Scoring!$B$23,"High",IF(Q69>=Scoring!$B$22,"Medium","Low")))) -> Medium | S69: =IF(Q69="","",IF(Q69<=Scoring!$B$27,"Yes","No")) -> Yes | T69: Mitigate | U69: Pre-draft notification templates per jurisdiction; add 72-hour clock to IR playbook. | V69: Privacy Counsel | W69: 46387 | X69: Open | Y69: Time to regulatory decision in exercises; templates maintained | Z69: 46264 | AA69: =IF(OR(Z69="",R69=""),"",Z69+INDEX(Scoring!$E$21:$E$24,MATCH(R69,Scoring!$A$21:$A$24,0))) -> 46444 | AB69: =IF(Q69="","",Q69+(1000-ROW())/100000) -> 6.00931
A70: R-065 | B70: 46252 | C70: Cyber: Threat & Incident Response | D70: Security tool sprawl and alert fatigue in the SOC | E70: Too many overlapping tools and noisy alerts could cause analysts to miss genuine incidents. | F70: SOC tooling and analysts | G70: Head of Security Operations | H70: 4 | I70: 3 | J70: =IF(OR(H70="",I70=""),"",H70*I70) -> 12 | K70: =IF(J70="","",IF(J70>=Scoring!$B$24,"Critical",IF(J70>=Scoring!$B$23,"High",IF(J70>=Scoring!$B$22,"Medium","Low")))) -> High | L70: Quarterly alert tuning; triage playbooks; ticketing integration. | M70: ISO 27001 A.8.16 | NIST DE.AE, GV.RR | N70: Weak | O70: 3 | P70: 2 | Q70: =IF(OR(O70="",P70=""),"",O70*P70) -> 6 | R70: =IF(Q70="","",IF(Q70>=Scoring!$B$24,"Critical",IF(Q70>=Scoring!$B$23,"High",IF(Q70>=Scoring!$B$22,"Medium","Low")))) -> Medium | S70: =IF(Q70="","",IF(Q70<=Scoring!$B$27,"Yes","No")) -> Yes | T70: Mitigate | U70: Consolidate overlapping tools; automate top 10 alert types with SOAR. | V70: SOC Engineering Lead | W70: 46507 | X70: Open | Y70: Alerts per analyst per shift; false positive rate | Z70: 46271 | AA70: =IF(OR(Z70="",R70=""),"",Z70+INDEX(Scoring!$E$21:$E$24,MATCH(R70,Scoring!$A$21:$A$24,0))) -> 46451 | AB70: =IF(Q70="","",Q70+(1000-ROW())/100000) -> 6.0093
... A76: R-071 | B76: 46282 | C76: Cyber: OT & Third-Party | D76: Cloud provider concentration and outage | E76: Heavy reliance on one cloud provider and region means a prolonged outage could stop core applications. | F76: Primary cloud region | G76: Chief Information Officer | H76: 3 | I76: 4 | J76: =IF(OR(H76="",I76=""),"",H76*I76) -> 12 | K76: =IF(J76="","",IF(J76>=Scoring!$B$24,"Critical",IF(J76>=Scoring!$B$23,"High",IF(J76>=Scoring!$B$22,"Medium","Low")))) -> High | L76: Multi-AZ deployment; DR runbooks; defined RTO and RPO for tier-1 apps. | M76: ISO 27001 A.5.29, A.5.30, A.8.14 | NIST PR.IR, RC.RP | N76: Adequate | O76: 2 | P76: 3 | Q76: =IF(OR(O76="",P76=""),"",O76*P76) -> 6 | R76: =IF(Q76="","",IF(Q76>=Scoring!$B$24,"Critical",IF(Q76>=Scoring!$B$23,"High",IF(Q76>=Scoring!$B$22,"Medium","Low")))) -> Medium | S76: =IF(Q76="","",IF(Q76<=Scoring!$B$27,"Yes","No")) -> Yes | T76: Mitigate | U76: Run annual failover test to secondary region; evaluate multi-cloud for critical workloads. | V76: Head of Cloud Platform | W76: 46538 | X76: Open | Y76: DR test success; achieved RTO vs target | Z76: 46285 | AA76: =IF(OR(Z76="",R76=""),"",Z76+INDEX(Scoring!$E$21:$E$24,MATCH(R76,Scoring!$A$21:$A$24,0))) -> 46465 | AB76: =IF(Q76="","",Q76+(1000-ROW())/100000) -> 6.00924
A77: R-072 | B77: 46287 | C77: Cyber: OT & Third-Party | D77: Counterfeit or tampered hardware in IT and OT procurement | E77: Tampered network or plant equipment could contain backdoors or fail unexpectedly. | F77: Network and plant equipment | G77: Chief Procurement Officer | H77: 2 | I77: 4 | J77: =IF(OR(H77="",I77=""),"",H77*I77) -> 8 | K77: =IF(J77="","",IF(J77>=Scoring!$B$24,"Critical",IF(J77>=Scoring!$B$23,"High",IF(J77>=Scoring!$B$22,"Medium","Low")))) -> Medium | L77: Approved vendor list; authorised reseller requirement; receiving inspection. | M77: ISO 27001 A.5.21, A.5.22 | NIST GV.SC | N77: Adequate | O77: 1 | P77: 4 | Q77: =IF(OR(O77="",P77=""),"",O77*P77) -> 4 | R77: =IF(Q77="","",IF(Q77>=Scoring!$B$24,"Critical",IF(Q77>=Scoring!$B$23,"High",IF(Q77>=Scoring!$B$22,"Medium","Low")))) -> Low | S77: =IF(Q77="","",IF(Q77<=Scoring!$B$27,"Yes","No")) -> Yes | T77: Accept | U77: Accept residual risk; maintain approved vendor list and spot-check serial numbers. | V77: IT Procurement Lead | X77: Monitoring | Y77: Purchases outside approved vendors | Z77: 46290 | AA77: =IF(OR(Z77="",R77=""),"",Z77+INDEX(Scoring!$E$21:$E$24,MATCH(R77,Scoring!$A$21:$A$24,0))) -> 46655 | AB77: =IF(Q77="","",Q77+(1000-ROW())/100000) -> 4.00923
A78: R-073 | B78: 46292 | C78: Cyber: OT & Third-Party | D78: Weak security clauses in supplier contracts | E78: Older contracts lack breach notification, audit rights and security standards, limiting leverage after an incident. | F78: Supplier contracts | G78: General Counsel | H78: 3 | I78: 3 | J78: =IF(OR(H78="",I78=""),"",H78*I78) -> 9 | K78: =IF(J78="","",IF(J78>=Scoring!$B$24,"Critical",IF(J78>=Scoring!$B$23,"High",IF(J78>=Scoring!$B$22,"Medium","Low")))) -> Medium | L78: Standard security schedule for new critical contracts; legacy contracts not updated. | M78: ISO 27001 A.5.20, A.5.22 | NIST GV.SC | N78: Weak | O78: 2 | P78: 3 | Q78: =IF(OR(O78="",P78=""),"",O78*P78) -> 6 | R78: =IF(Q78="","",IF(Q78>=Scoring!$B$24,"Critical",IF(Q78>=Scoring!$B$23,"High",IF(Q78>=Scoring!$B$22,"Medium","Low")))) -> Medium | S78: =IF(Q78="","",IF(Q78<=Scoring!$B$27,"Yes","No")) -> Yes | T78: Mitigate | U78: Update top 50 legacy contracts at renewal; require breach notification within 48 hours. | V78: Commercial Legal Lead | W78: 46568 | X78: Open | Y78: % critical contracts with security schedule | Z78: 46295 | AA78: =IF(OR(Z78="",R78=""),"",Z78+INDEX(Scoring!$E$21:$E$24,MATCH(R78,Scoring!$A$21:$A$24,0))) -> 46475 | AB78: =IF(Q78="","",Q78+(1000-ROW())/100000) -> 6.00922
A79: R-074 | B79: 46297 | C79: Cyber: OT & Third-Party | D79: Fourth-party cyber exposure through supplier subcontractors | E79: A supplier's own suppliers may have weak security, creating hidden paths to Meridian data and operations. | F79: Critical supply chain software | G79: Chief Procurement Officer | H79: 3 | I79: 3 | J79: =IF(OR(H79="",I79=""),"",H79*I79) -> 9 | K79: =IF(J79="","",IF(J79>=Scoring!$B$24,"Critical",IF(J79>=Scoring!$B$23,"High",IF(J79>=Scoring!$B$22,"Medium","Low")))) -> Medium | L79: Critical vendors asked to disclose key subcontractors; limited verification. | M79: ISO 27001 A.5.19, A.5.21 | NIST GV.SC | N79: Weak | O79: 3 | P79: 2 | Q79: =IF(OR(O79="",P79=""),"",O79*P79) -> 6 | R79: =IF(Q79="","",IF(Q79>=Scoring!$B$24,"Critical",IF(Q79>=Scoring!$B$23,"High",IF(Q79>=Scoring!$B$22,"Medium","Low")))) -> Medium | S79: =IF(Q79="","",IF(Q79<=Scoring!$B$27,"Yes","No")) -> Yes | T79: Mitigate | U79: Require subcontractor lists and flow-down security clauses for critical vendors. | V79: Vendor Risk Manager | W79: 46507 | X79: Open | Y79: Critical vendors with subcontractor map | Z79: 46300 | AA79: =IF(OR(Z79="",R79=""),"",Z79+INDEX(Scoring!$E$21:$E$24,MATCH(R79,Scoring!$A$21:$A$24,0))) -> 46480 | AB79: =IF(Q79="","",Q79+(1000-ROW())/100000) -> 6.00921
A80: R-075 | B80: 46302 | C80: Cyber: OT & Third-Party | D80: Cyber insurance gaps and exclusions | E80: Policy limits or exclusions (e.g. war, systemic events) could leave large losses uninsured after a major cyber event. | F80: Cyber insurance policy | G80: Chief Financial Officer | H80: 3 | I80: 4 | J80: =IF(OR(H80="",I80=""),"",H80*I80) -> 12 | K80: =IF(J80="","",IF(J80>=Scoring!$B$24,"Critical",IF(J80>=Scoring!$B$23,"High",IF(J80>=Scoring!$B$22,"Medium","Low")))) -> High | L80: Annual policy review with broker; insurer security questionnaire completed. | M80: ISO 31000 6.5 | NIST GV.RM | N80: Adequate | O80: 2 | P80: 3 | Q80: =IF(OR(O80="",P80=""),"",O80*P80) -> 6 | R80: =IF(Q80="","",IF(Q80>=Scoring!$B$24,"Critical",IF(Q80>=Scoring!$B$23,"High",IF(Q80>=Scoring!$B$22,"Medium","Low")))) -> Medium | S80: =IF(Q80="","",IF(Q80<=Scoring!$B$27,"Yes","No")) -> Yes | T80: Transfer | U80: Review war and systemic-event exclusions; align limits to modelled ransomware loss. | V80: Group Risk Manager | W80: 46387 | X80: Open | Y80: Policy limit vs modelled loss; exclusions reviewed | Z80: 46305 | AA80: =IF(OR(Z80="",R80=""),"",Z80+INDEX(Scoring!$E$21:$E$24,MATCH(R80,Scoring!$A$21:$A$24,0))) -> 46485 | AB80: =IF(Q80="","",Q80+(1000-ROW())/100000) -> 6.0092
J81: =IF(OR(H81="",I81=""),"",H81*I81) | K81: =IF(J81="","",IF(J81>=Scoring!$B$24,"Critical",IF(J81>=Scoring!$B$23,"High",IF(J81>=Scoring!$B$22,"Medium","Low")))) | Q81: =IF(OR(O81="",P81=""),"",O81*P81) | R81: =IF(Q81="","",IF(Q81>=Scoring!$B$24,"Critical",IF(Q81>=Scoring!$B$23,"High",IF(Q81>=Scoring!$B$22,"Medium","Low")))) | S81: =IF(Q81="","",IF(Q81<=Scoring!$B$27,"Yes","No")) | AA81: =IF(OR(Z81="",R81=""),"",Z81+INDEX(Scoring!$E$21:$E$24,MATCH(R81,Scoring!$A$21:$A$24,0))) | AB81: =IF(Q81="","",Q81+(1000-ROW())/100000)
J82: =IF(OR(H82="",I82=""),"",H82*I82) | K82: =IF(J82="","",IF(J82>=Scoring!$B$24,"Critical",IF(J82>=Scoring!$B$23,"High",IF(J82>=Scoring!$B$22,"Medium","Low")))) | Q82: =IF(OR(O82="",P82=""),"",O82*P82) | R82: =IF(Q82="","",IF(Q82>=Scoring!$B$24,"Critical",IF(Q82>=Scoring!$B$23,"High",IF(Q82>=Scoring!$B$22,"Medium","Low")))) | S82: =IF(Q82="","",IF(Q82<=Scoring!$B$27,"Yes","No")) | AA82: =IF(OR(Z82="",R82=""),"",Z82+INDEX(Scoring!$E$21:$E$24,MATCH(R82,Scoring!$A$21:$A$24,0))) | AB82: =IF(Q82="","",Q82+(1000-ROW())/100000)
J83: =IF(OR(H83="",I83=""),"",H83*I83) | K83: =IF(J83="","",IF(J83>=Scoring!$B$24,"Critical",IF(J83>=Scoring!$B$23,"High",IF(J83>=Scoring!$B$22,"Medium","Low")))) | Q83: =IF(OR(O83="",P83=""),"",O83*P83) | R83: =IF(Q83="","",IF(Q83>=Scoring!$B$24,"Critical",IF(Q83>=Scoring!$B$23,"High",IF(Q83>=Scoring!$B$22,"Medium","Low")))) | S83: =IF(Q83="","",IF(Q83<=Scoring!$B$27,"Yes","No")) | AA83: =IF(OR(Z83="",R83=""),"",Z83+INDEX(Scoring!$E$21:$E$24,MATCH(R83,Scoring!$A$21:$A$24,0))) | AB83: =IF(Q83="","",Q83+(1000-ROW())/100000)
J84: =IF(OR(H84="",I84=""),"",H84*I84) | K84: =IF(J84="","",IF(J84>=Scoring!$B$24,"Critical",IF(J84>=Scoring!$B$23,"High",IF(J84>=Scoring!$B$22,"Medium","Low")))) | Q84: =IF(OR(O84="",P84=""),"",O84*P84) | R84: =IF(Q84="","",IF(Q84>=Scoring!$B$24,"Critical",IF(Q84>=Scoring!$B$23,"High",IF(Q84>=Scoring!$B$22,"Medium","Low")))) | S84: =IF(Q84="","",IF(Q84<=Scoring!$B$27,"Yes","No")) | AA84: =IF(OR(Z84="",R84=""),"",Z84+INDEX(Scoring!$E$21:$E$24,MATCH(R84,Scoring!$A$21:$A$24,0))) | AB84: =IF(Q84="","",Q84+(1000-ROW())/100000)
J85: =IF(OR(H85="",I85=""),"",H85*I85) | K85: =IF(J85="","",IF(J85>=Scoring!$B$24,"Critical",IF(J85>=Scoring!$B$23,"High",IF(J85>=Scoring!$B$22,"Medium","Low")))) | Q85: =IF(OR(O85="",P85=""),"",O85*P85) | R85: =IF(Q85="","",IF(Q85>=Scoring!$B$24,"Critical",IF(Q85>=Scoring!$B$23,"High",IF(Q85>=Scoring!$B$22,"Medium","Low")))) | S85: =IF(Q85="","",IF(Q85<=Scoring!$B$27,"Yes","No")) | AA85: =IF(OR(Z85="",R85=""),"",Z85+INDEX(Scoring!$E$21:$E$24,MATCH(R85,Scoring!$A$21:$A$24,0))) | AB85: =IF(Q85="","",Q85+(1000-ROW())/100000)
J86: =IF(OR(H86="",I86=""),"",H86*I86) | K86: =IF(J86="","",IF(J86>=Scoring!$B$24,"Critical",IF(J86>=Scoring!$B$23,"High",IF(J86>=Scoring!$B$22,"Medium","Low")))) | Q86: =IF(OR(O86="",P86=""),"",O86*P86) | R86: =IF(Q86="","",IF(Q86>=Scoring!$B$24,"Critical",IF(Q86>=Scoring!$B$23,"High",IF(Q86>=Scoring!$B$22,"Medium","Low")))) | S86: =IF(Q86="","",IF(Q86<=Scoring!$B$27,"Yes","No")) | AA86: =IF(OR(Z86="",R86=""),"",Z86+INDEX(Scoring!$E$21:$E$24,MATCH(R86,Scoring!$A$21:$A$24,0))) | AB86: =IF(Q86="","",Q86+(1000-ROW())/100000)
J87: =IF(OR(H87="",I87=""),"",H87*I87) | K87: =IF(J87="","",IF(J87>=Scoring!$B$24,"Critical",IF(J87>=Scoring!$B$23,"High",IF(J87>=Scoring!$B$22,"Medium","Low")))) | Q87: =IF(OR(O87="",P87=""),"",O87*P87) | R87: =IF(Q87="","",IF(Q87>=Scoring!$B$24,"Critical",IF(Q87>=Scoring!$B$23,"High",IF(Q87>=Scoring!$B$22,"Medium","Low")))) | S87: =IF(Q87="","",IF(Q87<=Scoring!$B$27,"Yes","No")) | AA87: =IF(OR(Z87="",R87=""),"",Z87+INDEX(Scoring!$E$21:$E$24,MATCH(R87,Scoring!$A$21:$A$24,0))) | AB87: =IF(Q87="","",Q87+(1000-ROW())/100000)
J88: =IF(OR(H88="",I88=""),"",H88*I88) | K88: =IF(J88="","",IF(J88>=Scoring!$B$24,"Critical",IF(J88>=Scoring!$B$23,"High",IF(J88>=Scoring!$B$22,"Medium","Low")))) | Q88: =IF(OR(O88="",P88=""),"",O88*P88) | R88: =IF(Q88="","",IF(Q88>=Scoring!$B$24,"Critical",IF(Q88>=Scoring!$B$23,"High",IF(Q88>=Scoring!$B$22,"Medium","Low")))) | S88: =IF(Q88="","",IF(Q88<=Scoring!$B$27,"Yes","No")) | AA88: =IF(OR(Z88="",R88=""),"",Z88+INDEX(Scoring!$E$21:$E$24,MATCH(R88,Scoring!$A$21:$A$24,0))) | AB88: =IF(Q88="","",Q88+(1000-ROW())/100000)
J89: =IF(OR(H89="",I89=""),"",H89*I89) | K89: =IF(J89="","",IF(J89>=Scoring!$B$24,"Critical",IF(J89>=Scoring!$B$23,"High",IF(J89>=Scoring!$B$22,"Medium","Low")))) | Q89: =IF(OR(O89="",P89=""),"",O89*P89) | R89: =IF(Q89="","",IF(Q89>=Scoring!$B$24,"Critical",IF(Q89>=Scoring!$B$23,"High",IF(Q89>=Scoring!$B$22,"Medium","Low")))) | S89: =IF(Q89="","",IF(Q89<=Scoring!$B$27,"Yes","No")) | AA89: =IF(OR(Z89="",R89=""),"",Z89+INDEX(Scoring!$E$21:$E$24,MATCH(R89,Scoring!$A$21:$A$24,0))) | AB89: =IF(Q89="","",Q89+(1000-ROW())/100000)
J90: =IF(OR(H90="",I90=""),"",H90*I90) | K90: =IF(J90="","",IF(J90>=Scoring!$B$24,"Critical",IF(J90>=Scoring!$B$23,"High",IF(J90>=Scoring!$B$22,"Medium","Low")))) | Q90: =IF(OR(O90="",P90=""),"",O90*P90) | R90: =IF(Q90="","",IF(Q90>=Scoring!$B$24,"Critical",IF(Q90>=Scoring!$B$23,"High",IF(Q90>=Scoring!$B$22,"Medium","Low")))) | S90: =IF(Q90="","",IF(Q90<=Scoring!$B$27,"Yes","No")) | AA90: =IF(OR(Z90="",R90=""),"",Z90+INDEX(Scoring!$E$21:$E$24,MATCH(R90,Scoring!$A$21:$A$24,0))) | AB90: =IF(Q90="","",Q90+(1000-ROW())/100000)
J91: =IF(OR(H91="",I91=""),"",H91*I91) | K91: =IF(J91="","",IF(J91>=Scoring!$B$24,"Critical",IF(J91>=Scoring!$B$23,"High",IF(J91>=Scoring!$B$22,"Medium","Low")))) | Q91: =IF(OR(O91="",P91=""),"",O91*P91) | R91: =IF(Q91="","",IF(Q91>=Scoring!$B$24,"Critical",IF(Q91>=Scoring!$B$23,"High",IF(Q91>=Scoring!$B$22,"Medium","Low")))) | S91: =IF(Q91="","",IF(Q91<=Scoring!$B$27,"Yes","No")) | AA91: =IF(OR(Z91="",R91=""),"",Z91+INDEX(Scoring!$E$21:$E$24,MATCH(R91,Scoring!$A$21:$A$24,0))) | AB91: =IF(Q91="","",Q91+(1000-ROW())/100000)
J92: =IF(OR(H92="",I92=""),"",H92*I92) | K92: =IF(J92="","",IF(J92>=Scoring!$B$24,"Critical",IF(J92>=Scoring!$B$23,"High",IF(J92>=Scoring!$B$22,"Medium","Low")))) | Q92: =IF(OR(O92="",P92=""),"",O92*P92) | R92: =IF(Q92="","",IF(Q92>=Scoring!$B$24,"Critical",IF(Q92>=Scoring!$B$23,"High",IF(Q92>=Scoring!$B$22,"Medium","Low")))) | S92: =IF(Q92="","",IF(Q92<=Scoring!$B$27,"Yes","No")) | AA92: =IF(OR(Z92="",R92=""),"",Z92+INDEX(Scoring!$E$21:$E$24,MATCH(R92,Scoring!$A$21:$A$24,0))) | AB92: =IF(Q92="","",Q92+(1000-ROW())/100000)
... J105: =IF(OR(H105="",I105=""),"",H105*I105) | K105: =IF(J105="","",IF(J105>=Scoring!$B$24,"Critical",IF(J105>=Scoring!$B$23,"High",IF(J105>=Scoring!$B$22,"Medium","Low")))) | Q105: =IF(OR(O105="",P105=""),"",O105*P105) | R105: =IF(Q105="","",IF(Q105>=Scoring!$B$24,"Critical",IF(Q105>=Scoring!$B$23,"High",IF(Q105>=Scoring!$B$22,"Medium","Low")))) | S105: =IF(Q105="","",IF(Q105<=Scoring!$B$27,"Yes","No")) | AA105: =IF(OR(Z105="",R105=""),"",Z105+INDEX(Scoring!$E$21:$E$24,MATCH(R105,Scoring!$A$21:$A$24,0))) | AB105: =IF(Q105="","",Q105+(1000-ROW())/100000)

Sheet Dashboard
A1: Enterprise Risk Dashboard
A2: All figures calculate live from the 'Risk Register' sheet.
A4: Key metrics | D4: Risk distribution by rating
A5: Total risks logged | B5: =COUNTA('Risk Register'!$A$6:$A$105) -> 75 | D5: Rating | E5: Inherent | F5: Residual
A6: Critical + High risks (inherent) | B6: =COUNTIF('Risk Register'!$K$6:$K$105,"Critical")+COUNTIF('Risk Register'!$K$6:$K$105,"High") -> 61 | D6: Low | E6: =COUNTIF('Risk Register'!$K$6:$K$105,$D6) -> 0 | F6: =COUNTIF('Risk Register'!$R$6:$R$105,$D6) -> 6
A7: Critical + High risks (residual) | B7: =COUNTIF('Risk Register'!$R$6:$R$105,"Critical")+COUNTIF('Risk Register'!$R$6:$R$105,"High") -> 12 | D7: Medium | E7: =COUNTIF('Risk Register'!$K$6:$K$105,$D7) -> 14 | F7: =COUNTIF('Risk Register'!$R$6:$R$105,$D7) -> 57
A8: Average inherent score | B8: =IFERROR(AVERAGE('Risk Register'!$J$6:$J$105),0) -> 12.626667 | D8: High | E8: =COUNTIF('Risk Register'!$K$6:$K$105,$D8) -> 36 | F8: =COUNTIF('Risk Register'!$R$6:$R$105,$D8) -> 11
A9: Average residual score | B9: =IFERROR(AVERAGE('Risk Register'!$Q$6:$Q$105),0) -> 7.72 | D9: Critical | E9: =COUNTIF('Risk Register'!$K$6:$K$105,$D9) -> 25 | F9: =COUNTIF('Risk Register'!$R$6:$R$105,$D9) -> 1
A10: Risk reduction from controls | B10: =IFERROR(1-B9/B8,0) -> 0.38859556 | D10: Total | E10: =SUM(E6:E9) -> 75 | F10: =SUM(F6:F9) -> 75
A11: Residual risks within appetite | B11: =IFERROR(COUNTIF('Risk Register'!$S$6:$S$105,"Yes")/B5,0) -> 0.84
A12: Open actions past target date | B12: =COUNTIFS('Risk Register'!$W$6:$W$105,"<"&TODAY(),'Risk Register'!$X$6:$X$105,"<>Closed",'Risk Register'!$X$6:$X$105,"<>") -> 4
A15: Risks by category | F15: Risks by status
A16: Category | B16: # Risks | C16: Avg inherent | D16: Avg residual | F16: Status | G16: # Risks
A17: =Lists!A2 -> Climate & Environment | B17: =COUNTIF('Risk Register'!$C$6:$C$105,A17) -> 2 | C17: =IFERROR(AVERAGEIF('Risk Register'!$C$6:$C$105,A17,'Risk Register'!$J$6:$J$105),0) -> 15.5 | D17: =IFERROR(AVERAGEIF('Risk Register'!$C$6:$C$105,A17,'Risk Register'!$Q$6:$Q$105),0) -> 10.5 | F17: =Lists!D2 -> Open | G17: =COUNTIF('Risk Register'!$X$6:$X$105,F17) -> 32
A18: =Lists!A3 -> Supply Chain & Logistics | B18: =COUNTIF('Risk Register'!$C$6:$C$105,A18) -> 3 | C18: =IFERROR(AVERAGEIF('Risk Register'!$C$6:$C$105,A18,'Risk Register'!$J$6:$J$105),0) -> 14.333333 | D18: =IFERROR(AVERAGEIF('Risk Register'!$C$6:$C$105,A18,'Risk Register'!$Q$6:$Q$105),0) -> 10 | F18: =Lists!D3 -> In Progress | G18: =COUNTIF('Risk Register'!$X$6:$X$105,F18) -> 35
A19: =Lists!A4 -> Technology & AI | B19: =COUNTIF('Risk Register'!$C$6:$C$105,A19) -> 3 | C19: =IFERROR(AVERAGEIF('Risk Register'!$C$6:$C$105,A19,'Risk Register'!$J$6:$J$105),0) -> 13.333333 | D19: =IFERROR(AVERAGEIF('Risk Register'!$C$6:$C$105,A19,'Risk Register'!$Q$6:$Q$105),0) -> 8 | F19: =Lists!D4 -> Monitoring | G19: =COUNTIF('Risk Register'!$X$6:$X$105,F19) -> 6
A20: =Lists!A5 -> Workforce & Operating Model | B20: =COUNTIF('Risk Register'!$C$6:$C$105,A20) -> 4 | C20: =IFERROR(AVERAGEIF('Risk Register'!$C$6:$C$105,A20,'Risk Register'!$J$6:$J$105),0) -> 11.25 | D20: =IFERROR(AVERAGEIF('Risk Register'!$C$6:$C$105,A20,'Risk Register'!$Q$6:$Q$105),0) -> 6.75 | F20: =Lists!D5 -> Closed | G20: =COUNTIF('Risk Register'!$X$6:$X$105,F20) -> 2
A21: =Lists!A6 -> Regulatory & ESG | B21: =COUNTIF('Risk Register'!$C$6:$C$105,A21) -> 3 | C21: =IFERROR(AVERAGEIF('Risk Register'!$C$6:$C$105,A21,'Risk Register'!$J$6:$J$105),0) -> 12 | D21: =IFERROR(AVERAGEIF('Risk Register'!$C$6:$C$105,A21,'Risk Register'!$Q$6:$Q$105),0) -> 7.6666667
A22: =Lists!A7 -> Financial & Market | B22: =COUNTIF('Risk Register'!$C$6:$C$105,A22) -> 2 | C22: =IFERROR(AVERAGEIF('Risk Register'!$C$6:$C$105,A22,'Risk Register'!$J$6:$J$105),0) -> 14 | D22: =IFERROR(AVERAGEIF('Risk Register'!$C$6:$C$105,A22,'Risk Register'!$Q$6:$Q$105),0) -> 9
A23: =Lists!A8 -> Operational Resilience | B23: =COUNTIF('Risk Register'!$C$6:$C$105,A23) -> 2 | C23: =IFERROR(AVERAGEIF('Risk Register'!$C$6:$C$105,A23,'Risk Register'!$J$6:$J$105),0) -> 9 | D23: =IFERROR(AVERAGEIF('Risk Register'!$C$6:$C$105,A23,'Risk Register'!$Q$6:$Q$105),0) -> 7 | F23: Risks by treatment
A24: =Lists!A9 -> Cyber: Identity & Access | B24: =COUNTIF('Risk Register'!$C$6:$C$105,A24) -> 10 | C24: =IFERROR(AVERAGEIF('Risk Register'!$C$6:$C$105,A24,'Risk Register'!$J$6:$J$105),0) -> 12.7 | D24: =IFERROR(AVERAGEIF('Risk Register'!$C$6:$C$105,A24,'Risk Register'!$Q$6:$Q$105),0) -> 7 | F24: Treatment | G24: # Risks
A25: =Lists!A10 -> Cyber: Network & Infrastructure | B25: =COUNTIF('Risk Register'!$C$6:$C$105,A25) -> 8 | C25: =IFERROR(AVERAGEIF('Risk Register'!$C$6:$C$105,A25,'Risk Register'!$J$6:$J$105),0) -> 12.25 | D25: =IFERROR(AVERAGEIF('Risk Register'!$C$6:$C$105,A25,'Risk Register'!$Q$6:$Q$105),0) -> 8.375 | F25: =Lists!C2 -> Mitigate | G25: =COUNTIF('Risk Register'!$T$6:$T$105,F25) -> 66
A26: =Lists!A11 -> Cyber: Data Protection & Privacy | B26: =COUNTIF('Risk Register'!$C$6:$C$105,A26) -> 8 | C26: =IFERROR(AVERAGEIF('Risk Register'!$C$6:$C$105,A26,'Risk Register'!$J$6:$J$105),0) -> 12.125 | D26: =IFERROR(AVERAGEIF('Risk Register'!$C$6:$C$105,A26,'Risk Register'!$Q$6:$Q$105),0) -> 7.125 | F26: =Lists!C3 -> Accept | G26: =COUNTIF('Risk Register'!$T$6:$T$105,F26) -> 4
A27: =Lists!A12 -> Cyber: Application & Cloud | B27: =COUNTIF('Risk Register'!$C$6:$C$105,A27) -> 10 | C27: =IFERROR(AVERAGEIF('Risk Register'!$C$6:$C$105,A27,'Risk Register'!$J$6:$J$105),0) -> 13.2 | D27: =IFERROR(AVERAGEIF('Risk Register'!$C$6:$C$105,A27,'Risk Register'!$Q$6:$Q$105),0) -> 7 | F27: =Lists!C4 -> Transfer | G27: =COUNTIF('Risk Register'!$T$6:$T$105,F27) -> 3
A28: =Lists!A13 -> Cyber: Threat & Incident Response | B28: =COUNTIF('Risk Register'!$C$6:$C$105,A28) -> 9 | C28: =IFERROR(AVERAGEIF('Risk Register'!$C$6:$C$105,A28,'Risk Register'!$J$6:$J$105),0) -> 12.333333 | D28: =IFERROR(AVERAGEIF('Risk Register'!$C$6:$C$105,A28,'Risk Register'!$Q$6:$Q$105),0) -> 7.4444444 | F28: =Lists!C5 -> Avoid | G28: =COUNTIF('Risk Register'!$T$6:$T$105,F28) -> 2
A29: =Lists!A14 -> Cyber: OT & Third-Party | B29: =COUNTIF('Risk Register'!$C$6:$C$105,A29) -> 11 | C29: =IFERROR(AVERAGEIF('Risk Register'!$C$6:$C$105,A29,'Risk Register'!$J$6:$J$105),0) -> 12.818182 | D29: =IFERROR(AVERAGEIF('Risk Register'!$C$6:$C$105,A29,'Risk Register'!$Q$6:$Q$105),0) -> 8.2727273
A31: Top 5 residual risks (ranked)
A32: Risk title | B32: Risk ID | C32: Residual score | D32: Residual rating | E32: Risk owner
A33: =IFERROR(INDEX('Risk Register'!$D$6:$D$105,MATCH(LARGE('Risk Register'!$AB$6:$AB$105,1),'Risk Register'!$AB$6:$AB$105,0)),"") -> Ransomware attack on corporate IT systems | B33: =IFERROR(INDEX('Risk Register'!$A$6:$A$105,MATCH(LARGE('Risk Register'!$AB$6:$AB$105,1),'Risk Register'!$AB$6:$AB$105,0)),"") -> R-061 | C33: =IFERROR(INDEX('Risk Register'!$Q$6:$Q$105,MATCH(LARGE('Risk Register'!$AB$6:$AB$105,1),'Risk Register'!$AB$6:$AB$105,0)),"") -> 15 | D33: =IFERROR(INDEX('Risk Register'!$R$6:$R$105,MATCH(LARGE('Risk Register'!$AB$6:$AB$105,1),'Risk Register'!$AB$6:$AB$105,0)),"") -> Critical | E33: =IFERROR(INDEX('Risk Register'!$G$6:$G$105,MATCH(LARGE('Risk Register'!$AB$6:$AB$105,1),'Risk Register'!$AB$6:$AB$105,0)),"") -> Chief Information Security Officer
A34: =IFERROR(INDEX('Risk Register'!$D$6:$D$105,MATCH(LARGE('Risk Register'!$AB$6:$AB$105,2),'Risk Register'!$AB$6:$AB$105,0)),"") -> Flooding and storm damage at coastal plants | B34: =IFERROR(INDEX('Risk Register'!$A$6:$A$105,MATCH(LARGE('Risk Register'!$AB$6:$AB$105,2),'Risk Register'!$AB$6:$AB$105,0)),"") -> R-002 | C34: =IFERROR(INDEX('Risk Register'!$Q$6:$Q$105,MATCH(LARGE('Risk Register'!$AB$6:$AB$105,2),'Risk Register'!$AB$6:$AB$105,0)),"") -> 12 | D34: =IFERROR(INDEX('Risk Register'!$R$6:$R$105,MATCH(LARGE('Risk Register'!$AB$6:$AB$105,2),'Risk Register'!$AB$6:$AB$105,0)),"") -> High | E34: =IFERROR(INDEX('Risk Register'!$G$6:$G$105,MATCH(LARGE('Risk Register'!$AB$6:$AB$105,2),'Risk Register'!$AB$6:$AB$105,0)),"") -> Chief Operating Officer
A35: =IFERROR(INDEX('Risk Register'!$D$6:$D$105,MATCH(LARGE('Risk Register'!$AB$6:$AB$105,3),'Risk Register'!$AB$6:$AB$105,0)),"") -> Single-source dependency for specialty packaging film | B35: =IFERROR(INDEX('Risk Register'!$A$6:$A$105,MATCH(LARGE('Risk Register'!$AB$6:$AB$105,3),'Risk Register'!$AB$6:$AB$105,0)),"") -> R-004 | C35: =IFERROR(INDEX('Risk Register'!$Q$6:$Q$105,MATCH(LARGE('Risk Register'!$AB$6:$AB$105,3),'Risk Register'!$AB$6:$AB$105,0)),"") -> 12 | D35: =IFERROR(INDEX('Risk Register'!$R$6:$R$105,MATCH(LARGE('Risk Register'!$AB$6:$AB$105,3),'Risk Register'!$AB$6:$AB$105,0)),"") -> High | E35: =IFERROR(INDEX('Risk Register'!$G$6:$G$105,MATCH(LARGE('Risk Register'!$AB$6:$AB$105,3),'Risk Register'!$AB$6:$AB$105,0)),"") -> Chief Procurement Officer
A36: =IFERROR(INDEX('Risk Register'!$D$6:$D$105,MATCH(LARGE('Risk Register'!$AB$6:$AB$105,4),'Risk Register'!$AB$6:$AB$105,0)),"") -> Ransomware targeting plant operational technology (OT) | B36: =IFERROR(INDEX('Risk Register'!$A$6:$A$105,MATCH(LARGE('Risk Register'!$AB$6:$AB$105,4),'Risk Register'!$AB$6:$AB$105,0)),"") -> R-012 | C36: =IFERROR(INDEX('Risk Register'!$Q$6:$Q$105,MATCH(LARGE('Risk Register'!$AB$6:$AB$105,4),'Risk Register'!$AB$6:$AB$105,0)),"") -> 12 | D36: =IFERROR(INDEX('Risk Register'!$R$6:$R$105,MATCH(LARGE('Risk Register'!$AB$6:$AB$105,4),'Risk Register'!$AB$6:$AB$105,0)),"") -> High | E36: =IFERROR(INDEX('Risk Register'!$G$6:$G$105,MATCH(LARGE('Risk Register'!$AB$6:$AB$105,4),'Risk Register'!$AB$6:$AB$105,0)),"") -> Chief Information Security Officer
A37: =IFERROR(INDEX('Risk Register'!$D$6:$D$105,MATCH(LARGE('Risk Register'!$AB$6:$AB$105,5),'Risk Register'!$AB$6:$AB$105,0)),"") -> Unpatched vulnerabilities on internet-facing systems | B37: =IFERROR(INDEX('Risk Register'!$A$6:$A$105,MATCH(LARGE('Risk Register'!$AB$6:$AB$105,5),'Risk Register'!$AB$6:$AB$105,0)),"") -> R-031 | C37: =IFERROR(INDEX('Risk Register'!$Q$6:$Q$105,MATCH(LARGE('Risk Register'!$AB$6:$AB$105,5),'Risk Register'!$AB$6:$AB$105,0)),"") -> 12 | D37: =IFERROR(INDEX('Risk Register'!$R$6:$R$105,MATCH(LARGE('Risk Register'!$AB$6:$AB$105,5),'Risk Register'!$AB$6:$AB$105,0)),"") -> High | E37: =IFERROR(INDEX('Risk Register'!$G$6:$G$105,MATCH(LARGE('Risk Register'!$AB$6:$AB$105,5),'Risk Register'!$AB$6:$AB$105,0)),"") -> Head of IT Operations

Sheet Heat Map
A1: Risk Heat Maps
A2: Cell values show the number of risks at each Likelihood x Impact combination (blank = none).
A4: Inherent risk (before controls)
A5: Likelihood | B5: Level | C5: Negligible | D5: Minor | E5: Moderate | F5: Major | G5: Severe
A6: Impact score > | C6: 1 | D6: 2 | E6: 3 | F6: 4 | G6: 5
A7: 5 | B7: Almost certain | C7: =COUNTIFS('Risk Register'!$H$6:$H$105,$A7,'Risk Register'!$I$6:$I$105,C$6) -> 0 | D7: =COUNTIFS('Risk Register'!$H$6:$H$105,$A7,'Risk Register'!$I$6:$I$105,D$6) -> 1 | E7: =COUNTIFS('Risk Register'!$H$6:$H$105,$A7,'Risk Register'!$I$6:$I$105,E$6) -> 1 | F7: =COUNTIFS('Risk Register'!$H$6:$H$105,$A7,'Risk Register'!$I$6:$I$105,F$6) -> 0 | G7: =COUNTIFS('Risk Register'!$H$6:$H$105,$A7,'Risk Register'!$I$6:$I$105,G$6) -> 0
A8: 4 | B8: Likely | C8: =COUNTIFS('Risk Register'!$H$6:$H$105,$A8,'Risk Register'!$I$6:$I$105,C$6) -> 0 | D8: =COUNTIFS('Risk Register'!$H$6:$H$105,$A8,'Risk Register'!$I$6:$I$105,D$6) -> 0 | E8: =COUNTIFS('Risk Register'!$H$6:$H$105,$A8,'Risk Register'!$I$6:$I$105,E$6) -> 15 | F8: =COUNTIFS('Risk Register'!$H$6:$H$105,$A8,'Risk Register'!$I$6:$I$105,F$6) -> 14 | G8: =COUNTIFS('Risk Register'!$H$6:$H$105,$A8,'Risk Register'!$I$6:$I$105,G$6) -> 2
A9: 3 | B9: Possible | C9: =COUNTIFS('Risk Register'!$H$6:$H$105,$A9,'Risk Register'!$I$6:$I$105,C$6) -> 0 | D9: =COUNTIFS('Risk Register'!$H$6:$H$105,$A9,'Risk Register'!$I$6:$I$105,D$6) -> 0 | E9: =COUNTIFS('Risk Register'!$H$6:$H$105,$A9,'Risk Register'!$I$6:$I$105,E$6) -> 10 | F9: =COUNTIFS('Risk Register'!$H$6:$H$105,$A9,'Risk Register'!$I$6:$I$105,F$6) -> 18 | G9: =COUNTIFS('Risk Register'!$H$6:$H$105,$A9,'Risk Register'!$I$6:$I$105,G$6) -> 8
A10: 2 | B10: Unlikely | C10: =COUNTIFS('Risk Register'!$H$6:$H$105,$A10,'Risk Register'!$I$6:$I$105,C$6) -> 0 | D10: =COUNTIFS('Risk Register'!$H$6:$H$105,$A10,'Risk Register'!$I$6:$I$105,D$6) -> 0 | E10: =COUNTIFS('Risk Register'!$H$6:$H$105,$A10,'Risk Register'!$I$6:$I$105,E$6) -> 0 | F10: =COUNTIFS('Risk Register'!$H$6:$H$105,$A10,'Risk Register'!$I$6:$I$105,F$6) -> 4 | G10: =COUNTIFS('Risk Register'!$H$6:$H$105,$A10,'Risk Register'!$I$6:$I$105,G$6) -> 2
A11: 1 | B11: Rare | C11: =COUNTIFS('Risk Register'!$H$6:$H$105,$A11,'Risk Register'!$I$6:$I$105,C$6) -> 0 | D11: =COUNTIFS('Risk Register'!$H$6:$H$105,$A11,'Risk Register'!$I$6:$I$105,D$6) -> 0 | E11: =COUNTIFS('Risk Register'!$H$6:$H$105,$A11,'Risk Register'!$I$6:$I$105,E$6) -> 0 | F11: =COUNTIFS('Risk Register'!$H$6:$H$105,$A11,'Risk Register'!$I$6:$I$105,F$6) -> 0 | G11: =COUNTIFS('Risk Register'!$H$6:$H$105,$A11,'Risk Register'!$I$6:$I$105,G$6) -> 0
A14: Residual risk (after controls)
A15: Likelihood | B15: Level | C15: Negligible | D15: Minor | E15: Moderate | F15: Major | G15: Severe
A16: Impact score > | C16: 1 | D16: 2 | E16: 3 | F16: 4 | G16: 5
A17: 5 | B17: Almost certain | C17: =COUNTIFS('Risk Register'!$O$6:$O$105,$A17,'Risk Register'!$P$6:$P$105,C$16) -> 0 | D17: =COUNTIFS('Risk Register'!$O$6:$O$105,$A17,'Risk Register'!$P$6:$P$105,D$16) -> 0 | E17: =COUNTIFS('Risk Register'!$O$6:$O$105,$A17,'Risk Register'!$P$6:$P$105,E$16) -> 0 | F17: =COUNTIFS('Risk Register'!$O$6:$O$105,$A17,'Risk Register'!$P$6:$P$105,F$16) -> 0 | G17: =COUNTIFS('Risk Register'!$O$6:$O$105,$A17,'Risk Register'!$P$6:$P$105,G$16) -> 0
A18: 4 | B18: Likely | C18: =COUNTIFS('Risk Register'!$O$6:$O$105,$A18,'Risk Register'!$P$6:$P$105,C$16) -> 0 | D18: =COUNTIFS('Risk Register'!$O$6:$O$105,$A18,'Risk Register'!$P$6:$P$105,D$16) -> 1 | E18: =COUNTIFS('Risk Register'!$O$6:$O$105,$A18,'Risk Register'!$P$6:$P$105,E$16) -> 1 | F18: =COUNTIFS('Risk Register'!$O$6:$O$105,$A18,'Risk Register'!$P$6:$P$105,F$16) -> 0 | G18: =COUNTIFS('Risk Register'!$O$6:$O$105,$A18,'Risk Register'!$P$6:$P$105,G$16) -> 0
A19: 3 | B19: Possible | C19: =COUNTIFS('Risk Register'!$O$6:$O$105,$A19,'Risk Register'!$P$6:$P$105,C$16) -> 0 | D19: =COUNTIFS('Risk Register'!$O$6:$O$105,$A19,'Risk Register'!$P$6:$P$105,D$16) -> 14 | E19: =COUNTIFS('Risk Register'!$O$6:$O$105,$A19,'Risk Register'!$P$6:$P$105,E$16) -> 18 | F19: =COUNTIFS('Risk Register'!$O$6:$O$105,$A19,'Risk Register'!$P$6:$P$105,F$16) -> 10 | G19: =COUNTIFS('Risk Register'!$O$6:$O$105,$A19,'Risk Register'!$P$6:$P$105,G$16) -> 1
A20: 2 | B20: Unlikely | C20: =COUNTIFS('Risk Register'!$O$6:$O$105,$A20,'Risk Register'!$P$6:$P$105,C$16) -> 0 | D20: =COUNTIFS('Risk Register'!$O$6:$O$105,$A20,'Risk Register'!$P$6:$P$105,D$16) -> 1 | E20: =COUNTIFS('Risk Register'!$O$6:$O$105,$A20,'Risk Register'!$P$6:$P$105,E$16) -> 17 | F20: =COUNTIFS('Risk Register'!$O$6:$O$105,$A20,'Risk Register'!$P$6:$P$105,F$16) -> 7 | G20: =COUNTIFS('Risk Register'!$O$6:$O$105,$A20,'Risk Register'!$P$6:$P$105,G$16) -> 0
A21: 1 | B21: Rare | C21: =COUNTIFS('Risk Register'!$O$6:$O$105,$A21,'Risk Register'!$P$6:$P$105,C$16) -> 0 | D21: =COUNTIFS('Risk Register'!$O$6:$O$105,$A21,'Risk Register'!$P$6:$P$105,D$16) -> 2 | E21: =COUNTIFS('Risk Register'!$O$6:$O$105,$A21,'Risk Register'!$P$6:$P$105,E$16) -> 0 | F21: =COUNTIFS('Risk Register'!$O$6:$O$105,$A21,'Risk Register'!$P$6:$P$105,F$16) -> 3 | G21: =COUNTIFS('Risk Register'!$O$6:$O$105,$A21,'Risk Register'!$P$6:$P$105,G$16) -> 0
A23: Legend: | B23: Low | C23: Medium | D23: High | E23: Critical

Sheet Scoring
A1: Scoring Criteria & Risk Appetite
A2: Edit the blue/yellow cells to recalibrate the whole workbook.
A3: A. Likelihood scale
A4: Score | B4: Level | C4: Description | D4: Indicative frequency / probability
A5: 5 | B5: Almost certain | C5: Expected to occur in most circumstances | D5: Multiple times per year / >70%
A6: 4 | B6: Likely | C6: Will probably occur | D6: About once a year / 40-70%
A7: 3 | B7: Possible | C7: Might occur at some time | D7: Once in 1-3 years / 20-40%
A8: 2 | B8: Unlikely | C8: Could occur but not expected | D8: Once in 3-10 years / 5-20%
A9: 1 | B9: Rare | C9: Only in exceptional circumstances | D9: Less often than once in 10 years / <5%
A11: B. Impact scale (use the highest-scoring dimension)
A12: Score | B12: Level | C12: Financial (illustrative) | D12: Operational | E12: Regulatory / Legal | F12: Reputational
A13: 5 | B13: Severe | C13: >$100M loss or EBITDA impact | D13: Multiple plants or key products unavailable >2 weeks | E13: Licence to operate at risk; major sanction; criminal liability | F13: Sustained international media coverage; loss of major retail customers
A14: 4 | B14: Major | C14: $25M-$100M | D14: Plant or key product line down 3 days to 2 weeks | E14: Formal enforcement action; material fines; import ban | F14: National media coverage; customer delistings
A15: 3 | B15: Moderate | C15: $5M-$25M | D15: Production degraded 1-3 days; delivery delays | E15: Regulatory inquiry or reportable incident | F15: Limited media; customer complaints; investor questions
A16: 2 | B16: Minor | C16: $1M-$5M | D16: Short disruption under 1 day | E16: Minor non-compliance, self-identified | F16: Internal awareness only
A17: 1 | B17: Negligible | C17: <$1M | D17: No noticeable disruption | E17: No regulatory implications | F17: No external awareness
A19: C. Rating bands, required response and review frequency
A20: Rating | B20: Min score | C20: Max score | D20: Required response | E20: Review frequency (days)
A21: Low | B21: 1 | C21: =B22-1 -> 4 | D21: Accept and monitor; manage through routine controls. | E21: 365
A22: Medium | B22: 5 | C22: =B23-1 -> 9 | D22: Manage with defined controls; owner reviews periodically. | E22: 180
A23: High | B23: 10 | C23: =B24-1 -> 14 | D23: Treatment plan required; senior management oversight. | E23: 90
A24: Critical | B24: 15 | C24: 25 | D24: Immediate action; escalate to executive / risk committee. | E24: 30
A26: D. Risk appetite
A27: Residual score at or below which a risk is within appetite | B27: 9 | C27: Assumption: Medium (9) or below is tolerable. Edit to match your organisation's board-approved appetite.

Sheet Lists
A1: Category | B1: Control Effectiveness | C1: Treatment | D1: Status
A2: Climate & Environment | B2: Strong | C2: Mitigate | D2: Open
A3: Supply Chain & Logistics | B3: Adequate | C3: Accept | D3: In Progress
A4: Technology & AI | B4: Weak | C4: Transfer | D4: Monitoring
A5: Workforce & Operating Model | C5: Avoid | D5: Closed
A6: Regulatory & ESG
A7: Financial & Market
A8: Operational Resilience
A9: Cyber: Identity & Access
A10: Cyber: Network & Infrastructure
A11: Cyber: Data Protection & Privacy
A12: Cyber: Application & Cloud
A13: Cyber: Threat & Incident Response
A14: Cyber: OT & Third-Party
